Workbook
Name \0: #REF!
Name \0: #REF!
Name \01: #REF!
Name \01: #REF!
Name \A: #REF!
Name \A: #REF!
Name \B: #REF!
Name \B: #REF!
Name \c: #REF!
Name \c: #REF!
Name \d: #REF!
Name \E: #REF!
Name \F: #REF!
Name \G: #REF!
Name \H: #REF!
Name \I: #REF!
Name \k: #N/A
Name \L: #REF!
Name \M: #REF!
Name \n: #N/A
Name \p: #REF!
Name \q: #REF!
Name \R: #REF!
Name \s: #REF!
Name \T: #REF!
Name \U: #REF!
Name \v: #REF!
Name \W: #REF!
Name \X: #REF!
Name \Y: #REF!
Name \Z: #REF!
Name _: #REF!
Name ________________DAT1: #REF!
Name ______________DAT1: #REF!
Name ______________new1: #REF!
Name _____________DAT2: #REF!
Name _____________DAT4: #REF!
Name _____________DAT5: #REF!
Name _____________DAT6: #REF!
Name _____________DAT7: #REF!
Name _____________DAT8: #REF!
Name _____________DHR1: #REF!
Name ____________DAT1: #REF!
Name ____________DAT2: #REF!
Name ____________DAT3: #REF!
Name ____________DAT4: #REF!
Name ____________DAT5: #REF!
Name ____________DAT6: #REF!
Name ____________DAT7: #REF!
Name ____________DAT8: #REF!
Name ___________DAT1: #REF!
Name ___________DAT2: #REF!
Name ___________DAT3: #REF!
Name ___________DAT4: #REF!
Name ___________DAT5: #REF!
Name ___________DAT6: #REF!
Name ___________DAT7: #REF!
Name ___________DAT8: #REF!
Name ___________DHR1: #REF!
Name ___________new1: #REF!

Sheet BS PnL
A2: ABC INDIA LIMITED
A3: REGD. OFFICE-….................................................................................
A4: Email- …................................., CIN- …....................................
A6: Balance Sheet as at 31st March, 2025
A8: Particulars | E8: Note No. | F8: As at March 31, 2025 | G8: As at March 31, 2024
A10: EQUITY AND LIABILITIES
A12: Shareholder's Funds
A13: Share Capital | E13: 3 | F13: ='Note 3 (Share Capital)'!H13 -> 99753600 | G13: ='Note 3 (Share Capital)'!L13 -> 16625600
A14: Reserves and Surplus | E14: 4 | F14: ='NOTE (4-12)'!E16 -> 1.2061986e+08 | G14: ='NOTE (4-12)'!F16 -> 1.4231087e+08
A16: Share Application Money
A18: Non-Current Liabilities
A19: Long-Term Borrowings | E19: 5 | F19: ='NOTE (4-12)'!E30 -> 0 | G19: ='NOTE (4-12)'!F30 -> 1.3328216e+08
A20: Deferred Tax Liabilities (Net) | E20: 6 | F20: ='NOTE (4-12)'!F38 -> 8587125.1 | G20: ='NOTE (4-12)'!F43 -> 7672601.3
A21: Other Long Term Liablities | E21: 7 | F21: ='NOTE (4-12)'!E49 -> 0 | G21: ='NOTE (4-12)'!F49 -> 0
A22: Long-Term Provisions | E22: 7 | F22: ='NOTE (4-12)'!E55 -> 2585438 | G22: ='NOTE (4-12)'!F55 -> 1293445
A24: Current Liabilities
A25: Short Term Borrowings | E25: 8 | F25: ='NOTE (4-12)'!E71 -> 0 | G25: ='NOTE (4-12)'!F71 -> 2.0073596e+08
A26: Trade Payables
A27: - Total outstanding dues of micro enterprises and small enterprises | E27: 9 | F27: ='NOTE (4-12)'!G80+'NOTE (4-12)'!G83 -> 77661336 | G27: {=SUM('NOTE (4-12)'!G91:H91+'NOTE (4-12)'!G94:H94)} -> 59693317
A28: - Total outstanding dues of creditors other than micro enterprises and small enterprises | F28: ='NOTE (4-12)'!G81 -> 19455514 | G28: ='NOTE (4-12)'!G92:H92 -> 22190924
A29: Other Current Liabilities | E29: 10 | F29: ='NOTE (4-12)'!E112 -> 60516717 | G29: ='NOTE (4-12)'!F112 -> 73762051
A30: Short-Term Provisions | E30: 11 | F30: ='NOTE (4-12)'!E120 -> 25114846 | G30: =+'NOTE (4-12)'!F120 -> 16942772
B32: TOTAL | F32: =SUM(F13:F31)+1 -> 4.1429443e+08 | G32: =SUM(G13:G31) -> 6.7450971e+08
A34: ASSETS
A36: Non Current Assets
A37: Property, Plant and Equipment and Intangible Assets | E37: 12
A38: - Property, Plant and Equipment | F38: ='Note 12 (PPE)'!J20+'Note 12 (PPE)'!J33 -> 2.550476e+08 | G38: 242430740
A39: - Intangible Assets | F39: ='Note 12 (PPE)'!J28 -> 263586.71 | G39: 341760
A40: Capital work-in-Progress | E40: 13 | F40: ='13.CWIP'!F14 -> 2163233.6 | G40: ='13.CWIP'!F15 -> 935397.77
A41: Non-Current Investments | E41: 14 | F41: ='Note (13-20)'!F16 -> 4380144.5 | G41: ='Note (13-20)'!G16 -> 4380145.5
A42: Other Non-current Assets | E42: 15 | F42: ='Note (13-20)'!F25 -> 21449620 | G42: ='Note (13-20)'!G25 -> 21967669
A44: Current Assets
A45: Inventories | E45: 16 | F45: =+'Note (13-20)'!F34 -> 2.07425e+08 | G45: =+'Note (13-20)'!G34 -> 1.2275682e+08
A46: Trade Receivables | E46: 17 | F46: ='Note (13-20)'!H46 -> 2.5345423e+08 | G46: ='Note (13-20)'!H56 -> 208083527
A47: Cash and Cash Equivalents | E47: 18 | F47: =+'Note (13-20)'!F63 -> 44416 | G47: =+'Note (13-20)'!G63 -> 48289.55
A48: Short-Term Loans and Advances | E48: 19 | F48: ='Note (13-20)'!F72 -> 56735251 | G48: ='Note (13-20)'!G72 -> 37355941
A49: Other Current Assets | E49: 20 | F49: =+'Note (13-20)'!F88 -> 42312004 | G49: =+'Note (13-20)'!G88-4 -> 36209410
B51: TOTAL | F51: =(SUM(F37:F49)) -> 8.4327509e+08 | G51: =SUM(G37:G49)+1 -> 6.7450971e+08
A54: Summary of significant accounting policies.
A55: The accompany notes are an integral part of the Financial Statements.
A57: As per our report of even date attached
A58: For ABC & Company | E58: For and on behalf of the Boards of Directors of
A59: Chartered Accountants
A60: F.R. NO. 0XXXXXX | E60: ABC INDIA LIMITED
A64: Partner Name | E64: Director Name | G64: Director Name
A65: Partner | E65: Director | G65: Director
A66: Membership No : XXXXXX | E66: DIN No. | G66: DIN No.
A67: Date : | E67: =A67 -> Date : | G67: =A67 -> Date :
A68: Place : | E68: Place : | G68: =+E68 -> Place :
A69: UDIN :
E72: (CFO) | G72: (Company Secretary)
A74: =A2 -> ABC INDIA LIMITED
A76: REGD. OFFICE-38, S/F, Near MCD Park, Mohammadpur, New Delhi, India-110066
A77: Email- …................................., CIN- …....................................
A79: Statement of Profit and Loss for the year April 01, 2024 to March 31, 2025
E81: Note No. | F81: For The Year Ended 31/03/2025 | G81: For The Year Ended 31/03/2024
A83: Revenue From Operation | E83: 21 | F83: ='Note 20-31'!C11 -> 1.0008488e+09 | G83: =+'Note 20-31'!D11 -> 1.0465235e+09
A84: Other Income | E84: 22 | F84: =+'Note 20-31'!C23 -> 9033712.5 | G84: =+'Note 20-31'!D23 -> 2016242
A86: Total Income (I) | F86: =SUM(F83:F84)-0.01 -> 1.0098825e+09 | G86: =SUM(G83:G84) -> 1.0485397e+09
A87: Expenses:
A88: Cost of Materials Consumed | E88: 23 | F88: ='Note 20-31'!C34 -> 3.6908163e+08 | G88: =+'Note 20-31'!D34 -> 4.9624671e+08
A89: Purchase of Stock-in-Trade | E89: 24 | F89: ='Note 20-31'!C42 -> 1.7776843e+08 | G89: =+'Note 20-31'!D42 -> 95333036
A90: Changes in Inventories of
A91: - Finished Goods | E91: 25 | F91: ='Note 20-31'!C50-'Note 20-31'!C56 -> -35831603 | G91: ='Note 20-31'!D50-'Note 20-31'!D56 -> -5925090.9
A92: - Stock-in-Trade | F92: ='Note 20-31'!C52-'Note 20-31'!C58 -> -45108851 | G92: ='Note 20-31'!D52-'Note 20-31'!D58 -> -30580074
A93: - WIP | F93: ='Note 20-31'!C51-'Note 20-31'!C57 -> -2735891.4 | G93: 0
A94: Finance Costs | E94: 28 | F94: =+'Note 20-31'!C116 -> 44288846 | G94: =+'Note 20-31'!D116 -> 36351752
A95: Depreciation and Amortization Cost | E95: =E37 -> 12 | F95: ='Note 12 (PPE)'!G36-'Note 12 (PPE)'!H36 -> 15899307 | G95: 14218230
A96: Employee Benefits Expense | E96: 26 | F96: =+'Note 20-31'!C71 -> 1.2696729e+08 | G96: =+'Note 20-31'!D71 -> 1.0238078e+08
A97: Other Expenses | E97: 27 | F97: ='Note 20-31'!C93 -> 2.694714e+08 | G97: ='Note 20-31'!D93 -> 2.6385604e+08
A99: Total Expenses (II) | F99: =SUM(F88:F97) -> 9.1980055e+08 | G99: =SUM(G88:G97)-1 -> 9.7188137e+08
A100: Profit/(Loss) Before Prior period, Exceptional and Extraordinary Items and Tax (I-II) | F100: =F86-F99 -> 90081940 | G100: =G86-G99 -> 76658323
A101: Prior Period Items (Net) | F101: 3996796.4 | G101: 0
A103: Profit/(Loss) Before Exceptional and Extraordinary Items and Tax | F103: =F100-F101-F102 -> 86085143 | G103: =G100-G101-G102 -> 76658323
A104: Exceptional and Extraordinary Items | F104: 0 | G104: 0
A105: Profit/(Loss) Tax | F105: =F103-F104 -> 86085143 | G105: =G103-G104 -> 76658323
A106: Less: Tax Expenses
A107: 1. Current Tax | E107: 29 | F107: ='Note 20-31'!C124 -> 23733634 | G107: ='Note 20-31'!D124 -> 16559164
A108: 2. Deferred Tax | E108: 6 | F108: 914523.89 | G108: ='NOTE (4-12)'!E43 -> 1560524.3
A109: Profit/Loss for the Period | F109: =F105-F107-F108 -> 61436985 | G109: =G105-G107-G108 -> 58538635
A110: Earnings Per Equity Share (Nominal value per share Rs.10 each) (PY Rs. 100 each)
A111: Basic (In Rupees) | E111: 30 | F111: ='Note 20-31'!C139 -> 6.1588739 | G111: ='Note 20-31'!D139 -> 352.09938
A112: Diluted (In Rupees) | E112: 30 | F112: ='Note 20-31'!C140 -> 6.1588739 | G112: ='Note 20-31'!D140 -> 352.09938
A114: Summary of significant accounting policies.
A115: =$A$55 -> The accompany notes are an integral part of the Financial Statements.
A117: As per our report of even date attached
A118: =A58 -> For ABC & Company | E118: For and on behalf of the Boards of Directors of
A119: =A59 -> Chartered Accountants | E119: =E60 -> ABC INDIA LIMITED
A120: =A60 -> F.R. NO. 0XXXXXX | E120: =E61 -> 0
A125: =A64 -> Partner Name | E125: Director Name | G125: Director Name
A126: Partner | E126: Director | G126: Director
A127: Membership No : XXXXXX | E127: DIN No. | G127: DIN No.
A128: =A67 -> Date : | E128: =A128 -> Date : | G128: =A128 -> Date :
A129: =+A68 -> Place : | E129: =+E68 -> Place : | G129: =E129 -> Place :
A130: =A69 -> UDIN :
E134: (CFO) | G134: (Company Secretary)

Sheet Cash Flow 
B2: ABC INDIA LIMITED
B3: ='BS PnL'!A3 -> REGD. OFFICE-….................................................................................
B4: Email- …................................., CIN- …....................................
B6: Cash Flow Statement for the year ended 31st March, 2025
B8: Particulars | D8: For the year ended 31 March, 2025 | E8: For the year ended 31 March, 2024
B10: Cash flows from operating activities
B11: Profit before taxation | D11: ='BS PnL'!F105 -> 86085143 | E11: 76658310
B12: Adjustments for:
B13: Depreciation | D13: ='Note 12 (PPE)'!G36 -> 15899307 | E13: 14218210
B14: Interest Income | D14: =-'Note 20-31'!C16-'Note 20-31'!C17 -> -2115554 | E14: -1586320
B15: Prior period adjustment to PPE | D15: 242760 | E15: 0
B16: Interest expense | D16: ='BS PnL'!F94 -> 44288846 | E16: ='BS PnL'!G94 -> 36351752
B17: Profit / (Loss) on the sale of property, plant & equipment | D17: =-'Note 20-31'!C19 -> 0 | E17: 0
B18: Working capital changes:
B19: (Increase) / Decrease in trade and other receivables | D19: =-'BS PnL'!J46-'BS PnL'!J49 -> 0 | E19: -101738230
B20: (Increase) / Decrease in inventories | D20: =-'BS PnL'!J45 -> 0 | E20: -46947690
B21: Increase / (Decrease) in trade and other payables | D21: =SUM('BS PnL'!J27:J28)+'BS PnL'!J29+'BS PnL'!J30-10.89 -> -10.89 | E21: 54285780
B22: Non Cash Adjusment to Reserves | D22: 0 | E22: 269
B23: Cash generated from operations | D23: =SUM(D11:D22) -> 1.4440049e+08 | E23: =SUM(E11:E22) -> 31242081
B24: Less: Interest paid | D24: ='BS PnL'!F94 -> 44288846 | E24: ='BS PnL'!G94 -> 36351752
B25: Less: Income taxes paid | D25: ='BS PnL'!F107 -> 23733634 | E25: ='BS PnL'!G107 -> 16559164
B26: Dividends paid | D26: 0 | E26: 0
B27: Net cash from operating activities | D27: =D23-D24-D25 -> 76378011 | E27: =E23-E24-E25 -> -21668835
B29: Cash flows from investing activities
B30: Purchase of property, plant and equipment | D30: =-'Note 12 (PPE)'!C36 -> -28680764 | E30: -12176160
B31: Cash Outflow in Capital work in progress | D31: =-'13.CWIP'!F14-E31 -> -1227813.6 | E31: -935420
B32: Proceeds from sale of equipment | D32: =-'Note 12 (PPE)'!D36 -> 0 | E32: 205410
B33: Sale/(Purchase) of Investment | D33: 0 | E33: 0
B34: Sale/(Purchase) of other Investment | D34: =-'BS PnL'!J42 -> 0 | E34: -8088945
B35: Investment income | D35: =-D14 -> 2115554 | E35: =-E14 -> 1586320
B36: Net cash used in investing activities | D36: =SUM(D29:D35) -> -27793024 | E36: =SUM(E29:E35) -> -19408795
B38: Cash flows from financing activities
B39: Proceeds from issue of share capital | D39: 0 | E39: 0
B40: Payment Recieved Long Term Loans and Advances | D40: 0 | E40: 0
B41: Amount Given as Short Terms Loans and Advances | D41: =-'BS PnL'!J48 -> 0 | E41: -10610395
B42: Payment Recieved Short Term Loans and Advances | D42: 0 | E42: 0
B43: Proceeds/(Payment) from long-term borrowings | D43: ='BS PnL'!J19 -> 0 | E43: -59258135
B44: Proceeds/(Payment) of Long-term Provision | D44: =+'BS PnL'!J22 -> 0 | E44: 1293445
B45: Payment of Short-term borrowings | D45: 0 | E45: 0
B46: Proceeds from Short-term borrowings | D46: ='BS PnL'!J25 -> 0 | E46: 106660255
B47: Net cash used in financing activities | D47: =SUM(D39:D46) -> 0 | E47: =SUM(E39:E46) -> 38085170
B49: Net increase in cash and cash equivalents | D49: =D27+D36+D47 -> 48584987 | E49: =E27+E36+E47 -> -2992460
B50: Cash and cash equivalents at beginning of period | D50: ='BS PnL'!G47 -> 48289.55 | E50: 3040750
B51: Cash and cash equivalents at end of period | D51: =D49+D50 -> 48633277 | E51: =E49+E50 -> 48290
B53: Cash and cash equivalents comprises (Refer to note)
B54: Cash in hand | D54: ='Note (13-20)'!F62 -> 43816 | E54: 23193
B55: Balances with banks on current accounts | D55: ='Note (13-20)'!F61 -> 600 | E55: 25097
D56: =D54+D55 -> 44416 | E56: =E54+E55-0.01 -> 48289.99 | G56: =+D51-D56 -> 48588861 | H56: =E51-E56 -> 0.0099999926
B58: Summary of significant accounting policies.
B59: The accompanying notes are an integral part of the financial statements.
B61: As per our report of even date attached
B62: =+'BS PnL'!A58 -> For ABC & Company | D62: For and on behalf of the Boards of Directors of
B63: Chartered Accountants | D63: ='BS PnL'!E60 -> ABC INDIA LIMITED
B64: =+'BS PnL'!A60 -> F.R. NO. 0XXXXXX
B69: =+'BS PnL'!A64 -> Partner Name | D69: Director Name | E69: Director Name
B70: =+'BS PnL'!A65 -> Partner | D70: Director | E70: Director
B71: =+'BS PnL'!A66 -> Membership No : XXXXXX | D71: DIN No. | E71: DIN No.
B72: ='BS PnL'!A67 -> Date : | D72: =B72 -> Date : | E72: =B72 -> Date :
B73: ='BS PnL'!A68 -> Place : | D73: =+'BS PnL'!E68 -> Place : | E73: =+D73 -> Place :
B74: ='BS PnL'!A69 -> UDIN :
D78: (CFO) | E78: (Company Secretary)

Sheet Note 1-2
A2: ABC INDIA LIMITED
A3: Notes forming part of the Financial Statements for the year ended March 31, 2025
A4: REGD. OFFICE- N-6, FIRST FLOOR, REAR SIDE, GREEN PARK MAIN, NEW DELHI-110016
A5: Factory Office:- Village Puruwala, Post Gorkhuwal, Paonta Sahib, District Sirmour, Himachal Pradesh-173025
A6: Email- Msarda@gabionindia.com, CIN- U74999DL2008PTC195317
A8: Note 1 | B8: Corporate Information
B10: ABC India Limited (‘the Company’) was incorporated in India on January 01, 2000 with its registered office in (State Name) at Registered Office Address......................................................................... The company is engaged in the business of (Company Object Clause).
A13: Note 2 | B13: Summary of Significant Accounting Policies
A15: 2.1 | B15: Basis of Presentation:
B17: The financial statements are prepared under the historical cost convention, on the accrual basis of accounting in accordance with the Generally Accepted Accounting Principles (‘GAAP’) in India and comply with the accounting standards prescribed under section 133 of the Companies Act, 2013("the Act") read with Rule 7 of the Companies(Accounts) Rules, 2024 the provisions of the Act (to the extent notified) .
A20: =A15+0.1 -> 2.2 | B20: Use of Estimates:
B22: The preparation of financial statements in conformity with generally accepted accounting principles requires management to make estimates and assumptions that affect the reported amounts of assets and liabilities and disclosure of contingent liabilities on the date of the financial statements and the results of operations during the period. Differences between actual results and estimates are recognised in the period in which the results are known or materialised. Examples of such estimates are estimated useful life of asset, etc. Any revision to accounting estimates is recognised in accordance with the requirements of the respective accounting standard.
A27: =A20+0.1 -> 2.3 | B27: Revenue Recognition:
B29: Revenue from sale of goods is recognised when the goods are dispatched to the customer which coincides with the transfer of risk and rewards in the goods. The sales are recorded at invoice value, net of taxes.
B31: Revenue from services is recognised propotionately by referance to the performance of each act. Revenue is only recognized when it can be reasonably measurable and at the time of rendering of the services it would not unreasonably to expect ultimate collection.
A34: =A27+0.1 -> 2.4 | B34: Income Taxes
B36: Income-tax expense comprises current tax (i.e. the amount of tax for the period determined in accordance with the Income-tax Act, 1961) and deferred tax charge or credit (reflecting the tax effects of timing differences between the accounting income and taxable income for the period). The deferred tax charge or credit and the corresponding deferred tax liabilities or assets are recognised using the tax rates that have been enacted or substantively enacted as on the balance sheet date. Deferred tax assets are recognised only to the extent there is reasonable certainty of its realization. However, where there is unabsorbed depreciation or carried forward loss under taxation laws, deferred tax assets are recognised only if there is virtual certainty supported by convincing evidence that they can be realized against future taxable profits. At each reporting date the company reassesses unrecognized deferred tax assets. It recognizes unrecognized deferred tax assets to the extent that it has become reasonably certain or virtually certain, as the case may be, that sufficient future taxable income will be available against which such deferred tax assets can be realized. The carrying amount of deferred tax assets are reviewed at each reporting date. The company writes down/up the carrying amount of deferred tax assets to the extent that it is no longer reasonably certain or virtually certain, as the case may be, that sufficient future taxable income will be available against which such deferred tax assets can be realized. Any such write down is reserved to the extent that it becomes reasonably certain or virtually certain, as the case may be, that sufficient future taxable income will be available.
A44: =A34+0.1 -> 2.5 | B44: Earning Per Share:
B46: The Company reports basic earnings per equity share in accordance with Accounting Standard 20, Earnings per Share. The Basic earnings per share is computed by dividing the net profit attributable to equity shareholders for the period by the weighted average number of equity shares outstanding during the period. The Company reports diluted earnings per equity share in accordance with Accounting Standard 20, Earnings per Share. The Diluted earnings per share is computed by the net profit or loss for the period attributable to equity shareholders and the weighted average number of shares outstanding during the period should be adjusted for the effects of all dilutive potential equity shares
A49: =A44+0.1 -> 2.6 | B49: Provisions and Contingent Liability
B51: Provision
B53: A provision is recognised when the Company has a present obligation as a result of a past event, it is probable that an outflow of resources embodying economic benefits will be required to settle the obligation and reliable estimate can be made of the amount of the obligation. A contingent liability is a possible obligation that arises from past events whose exixstence will be confirmed by the occurence or non-occurence of one or more uncertain future events beyond the control of company or a present obligation that is not recognised because it is not possible that an outflow of resources will be required to settle the obligation.
B58: Contigent Liability
B60: A contingent liability also arises in extreamly rare cases where there is liability that can not be recognised beause it can not be measured reliabily. The company does not recognise a contigent liability but discloses its existence in the financial statements. The Company does not recognise assets which are of contingent nature until there is virtual certainty of the realisation of such assets. However, if it has become virtually certain that an inflow of economic benefits will arise then asset and related income are recognised in the financial statements of the period in which the change occurs.
A62: =A49+0.1 -> 2.7 | B62: Measurement of EBITDA :
B64: The company has elected to present earning before interest, tax, depreciation & amortisation (EBITDA) as a separate line item on the face of statement of profit & loss. In its measurement, the company does not include depreciation, amortisation expense, finance cost and tax expense.
A68: =A62+0.1 -> 2.8 | B68: Cash and cash equivalents:
B69: Cash and cash equivalents comprise cash at bank and in hand and short-term investments with an original maturity of three months or less.
A71: 2.9 | B71: Property, Plant & Equipment:
B72: (a) Property, Plant & Equipment are stated at cost, less accumulated depreciation. The cost comprises the purchase price, borrowing cost if capitalization criteria are met and directly attributable cost of bringing the assets to its working condition for its intended use.
B73: (b) Subsequent expenditures related to an item of Property, Plant & Equipment is added to its book value only if its increases the future benefits from the existing asset beyond its previously assessed standard of performance. All other expenses on existing fixed assets, including day to day repair and maintenance expenditure and cost of replacing parts, are charged to the statement of profit and loss for the period during which such expenses are incurred.
B75: (c) Gains or losses arising from derecognition of Property, Plant & Equipment are measured as the difference between the net disposal proceeds and the carrying amount of asset and are recognized in the statement of profit and loss when the asset is derecognized.
A77: 2.1 | B77: Depreciation and amortisation of Property, Plant & Equipment:
B79: Depreciation on property, plant & equipment is provided on the basis of straight line method over the useful life of assets as specified under Schedule II of Company Act 2013.
B81: Depreciation on additions is provided on a pro-rata basis from the month of acquisition/installation. Depreciation on sale/deduction from fixed assets is provided for up to the date of sale/adjustment, as the case may be. Modification or extension to an existing asset, which is of capital nature and which becomes an integral part thereof is depreciated prospectively over the remaining useful life of that asset.
B82: All assets costing Rs. 5,000 or below are fully depreciated in the year of purchase.
B84: Leasehold improvements are amortized over the remaining period of the lease or useful life of the assets, whichever is shorter.
C85: Asset Category | F85: Life in Year | G85: Basis for useful life
C86: Plant & Machinery | F86: 5 & 15 | G86: Life as prescribed under Schedule-II of Companies Act, 2013
C87: Furniture & Fixtures | F87: 10
C88: Computer | F88: 3
C89: Office Equipments | F89: 5
C90: Vehicles | F90: 6 & 8
A91: 2.11 | B91: Intangible Assets
B92: Intangible assets acquired separately are measured on initial recognition at cost. Following initial recognition, intangible assets are carried at cost less any accumulated amortisation and accumulated impairment losses. Internally generated intangibles, excluding capitalised development costs, are not capitalised and the related expenditure is reflected in profit or loss in the period in which the expenditure is incurred.
B93: Amortisation is recognised on a straight-line basis over their estimated useful lives. The estimated useful life and amortisation method are reviewed at the end of each reporting period, with the effect of any changes in estimate being accounted for on a prospective basis.
B94: An intangible asset is derecognised on disposal, or when no future economic benefits are expected from use or disposal. Gains or losses arising from derecognition of an intangible asset, measured as the difference between the net disposal proceeds and the carrying amount of the asset, are recognised in statement of profit or loss when the asset is derecognised.
A96: 2.12 | B96: Foreign Currency Transaction:
B98: (a) Initial recognition:
B99: Foreign currency transactions are recorded in the reporting currency, by applying to the foreign currency amount and the exchange rate between the reporting currency and the foreign currency at the date of transaction.
B102: (b) Conversion:
B103: Foreign currency monetary items are retranslated using the exchange rate prevailing at the reporting date. Non-monetary items, which are measured in terms of historical cost denominated in foreign currency, are reported using the exchange rate at the date of transaction. Non-monetary items, which are carried at fair value or other similar valuation denominated in foreign currency, are translated using the exchange rate at the date when such value was determined.
B105: (c) Exchange differences:
B106: Exchange differences arising on translation/settlement of foreign currency monetary items are recognized as an income or as an expense in the period in which they arise.
A109: 2.13 | B109: Operating Leases:
B111: Leases, where the lessor effectively retains substantially all the risks and benefits of ownership of the leased items, are classified as operating leases. Operating lease payments are recognized as an expense in the statement of Profit and Loss on systematic basis over the lease term.
A113: 2.14 | B113: Borrowing Costs
B114: Borrowing Cost that are attributable to the acquisition or construction of qualifying assets are capitalized as part of the cost of the assets. A qualifying asset is one that necessarily takes substantial period of time to get ready for intended use . All Other borrowing costs are charged to the profit and loss account.
A116: 2.15 | B116: Inventories
B117: Inventories of raw materials, components, stores and spares are valued at lower of cost (net of recoverable taxes) and net realizable value. Cost for the purpose of valuation of such inventories is determined using the first-in, first-out (FIFO) method. Net realizable value is the estimated selling price in the ordinary course of business less the estimated cost of completion and the estimated cost necessary to make the sale.
B122: Finished goods and work-in-progress are valued at lower of cost and net realizable value. The cost of finished goods and work-in-progress includes raw material costs (net of recoverable taxes), direct cost of conversion and proportionate allocation of indirect costs incurred in bringing the inventories to their present location and condition.
B126: Stock-in-trade are valued at lower of cost (net of recoverable taxes) and net realizable value.
B128: The provision for inventory obsolescence is assessed regularly based on estimated usage and shelf life of inventory
A130: 2.16 | B130: Employee benefits
B131: (i) | C131: Short-term obligations
C132: Liabilities for wages and salaries, including non-monetary benefits that are expected to be settled wholly within twelve months after the end of the period in which the employees render the related service are recognised in respect of employees’ services up to the end of the reporting period and are measured at the undiscounted amounts expected to be paid when the liabilities are settled. The liabilities are presented as current benefit obligations in the balance sheet.
B134: (ii) | C134: Other long-term employee benefit obligations
C135: Other long-term employee benefits includes earned leaves, sick leaves and employee bonus.
C137: Earned leaves
C138: The liabilities for earned leaves are expected to be settled wholly within twelve months in which the employees render the related service. They are therefore are not measured at the present value of expected future payments to be made in respect of services provided by employees up to the end of the reporting period using the projected unit credit method.
B141: (iii) | C141: Post-employment obligations
C142: The Company operates the following post employment schemes:
C143: * | D143: defined benefit plan towards payment of gratuity; and
C144: * | D144: defined contribution plans towards provident fund & employee pension scheme and employee state insurance.
C146: Defined benefit plans
C147: The Company provides for gratuity obligations through a defined benefit retirement plan (the ‘Gratuity Plan’) covering all employees. The Gratuity Plan provides a lump sum payment to vested employees at retirement/termination of employment or death of an employee, based on the respective employees’ salary and years of employment with the Company.
C148: The liability or asset recognised in the balance sheet in respect of the defined benefit plan is the present value of the defined benefit obligation at the end of the reporting period less the fair value of plan assets. The present value of the defined benefit obligation is determined using projected unit credit method by discounting the estimated future cash outflows by reference to market yields at the end of the reporting period on government bonds that have terms approximating to the terms of the related obligation, with actuarial valuations being carried out at the end of each annual reporting period.
C149: The net interest cost is calculated by applying the discount rate to the net balance of the defined benefit obligation and the fair value of plan assets. This cost is included in employee benefit expense in the statement of profit and loss. Remeasurement gains and losses arising from experience adjustments and changes in actuarial assumptions are recognised in the period in which they occur, directly in other comprehensive income. They are included in retained earnings in the statement of changes in equity and in the balance sheet.
C151: Defined contribution plans
C152: Defined contribution plans are retirement benefit plans under which the Company pays fixed contributions to separate entities (funds) or financial institutions or state managed benefit schemes. The Company has no further payment obligations once the contributions have been paid. The defined contributions plans are recognised as employee benefit expense when they are due. Prepaid contributions are recognised as an asset to the extent that a cash refund or a reduction in the future payments is available.
C153: * | D153: Provident Fund Plan
D154: The Company makes monthly contributions at prescribed rates towards Employees’ Provident Fund to a Fund administered and managed by the Government of India.
C156: * | D156: Leave Encashment
D157: The Company has recognised liability for short term compensated absences on full cost basis with reference to unavailed earned leaves at the year end.
A158: 2.17 | C158: Investment
C159: Short Term Investment is valued at Cost or Net Realisable Value, whichever is lower. Long Term Investment is valued at cost on individual basis.

Sheet Note 3 (Share Capital)
A2: ='Note 1-2'!A2 -> ABC INDIA LIMITED
A3: ='Note 1-2'!A3 -> Notes forming part of the Financial Statements for the year ended March 31, 2025
A5: Note 3 | B5: SHARE CAPITAL
B7: Particulars | F7: As at March 31, 2025 | J7: As at March 31, 2024
F8: Number | H8: Amount Rs | J8: Number | L8: Amount Rs
B9: Authorised
B10: 1,60,00,000 Equity Shares of Rs 10 each | F10: =16000000 -> 16000000 | H10: =F10*10 -> 160000000 | J10: =300000 -> 300000 | L10: =J10*100 -> 30000000
B11: Issued, subscribed and fully paid up
B12: 99,75,360 Equity Shares of Rs 10 each | F12: 9975360 | H12: =F12*10 -> 99753600 | J12: 166256 | L12: =J12*100 -> 16625600
B13: Total | F13: =SUM(F12:F12) -> 9975360 | H13: =SUM(H12:H12) -> 99753600 | J13: =SUM(J12:J12) -> 166256 | L13: =SUM(L12:L12) -> 16625600
A15: a. | B15: Reconciliation of the shares oustanding at the beginning and at the end of the reporting period.
B17: Equity Shares
B18: Particulars | F18: As at March 31, 2025 | J18: As at March 31, 2024
F19: Number | H19: Amount Rs | J19: Number | L19: Amount Rs
B20: Share Outstanding at the beginning | F20: 166256 | H20: =F20*10 -> 1662560 | J20: =J12 -> 166256 | L20: =L12 -> 16625600
B21: Shares issued during the year | F21: =8312800+1496304 -> 9809104 | H21: =F21*10 -> 98091040 | J21: 0 | L21: 0
B22: Shares bought back during the year | F22: 0 | H22: 0 | J22: 0 | L22: 0
B23: Shares Outstanding at the end of the year | F23: =F20+F21-F22 -> 9975360 | H23: =H20+H21-H22 -> 99753600 | J23: =J20+J21-J22 -> 166256 | L23: =L20+L21-L22 -> 16625600
A26: b. | B26: Terms/rights attached to equity shares
B28: The company has only one class of equity shares having a par value of Rs 10 per share. Each holder of equity shares is entitled to one vote per share. The company declares and pays dividends in Indian rupees.In the event of liquidation, the equity shareholders are eligible to recieve the remaining assets of the company after distribution of all preferential amounts, in proportion to their shareholding.
A32: c. | B32: Aggregate number of bonus shares issued, share issued for consideration other than cash and shares bought back during the period of five years immediately preceding the reporting date.
B36: Particulars | F36: Year | H36: Year | J36: Year | L36: Year | N36: Year
F37: 2024-25 | H37: 2023-24 | J37: 2022-23 | L37: 2021-22 | N37: 2020-21
B38: Equity Shares :
B39: Fully paid up pursuant to contract(s) without payment being received in cash | F39: Nil | H39: Nil | J39: Nil | L39: Nil | N39: Nil
B41: Fully paid up by way of bonus shares | F41: 8312800 | H41: Nil | J41: Nil | L41: Nil | N41: Nil
B43: Shares bought back | F43: Nil | H43: Nil | J43: Nil | L43: Nil | N43: Nil
A46: d. | B46: Details of shareholders holding more than 5% shares in the company.
B48: Name of Shareholder | F48: As at March 31, 2025 | K48: As at March 31, 2024
B49: Shareholders:- | F49: No. of Shares Held | H49: % of Holding | J49: % Change in Holding | K49: No. of Shares Held | M49: % of Holding | O49: % Change in Holding
H51: =F51/9975360 -> 0 | J51: =H51-M51 -> 0 | M51: =K51/166256 -> 0 | O51: 0
H53: =F53/9975360 -> 0 | J53: =H53-M53 -> 0 | M53: =K53/166256 -> 0 | O53: 0
H55: =F55/9975360 -> 0 | J55: =H55-M55 -> 0 | M55: 0 | O55: 0
M56: 0 | O56: 0
H57: =F57/9975360 -> 0 | J57: =H57-M57 -> 0 | M57: =K57/166256 -> 0 | O57: 0
A61: e. | B61: Details of shareholders holding hold by Promoters of company.
B63: Name of Promoters | F63: As at March 31, 2025 | K63: As at March 31, 2024
B64: Promoters:- | F64: No. of Shares Held | H64: % of Holding | J64: % Change in Holding | K64: No. of Shares Held | M64: % of Holding | O64: % Change in Holding
H66: =F66/9975360 -> 0 | J66: =H66-M66 -> 0 | O66: 0
H68: =F68/9975360 -> 0 | J68: =H68-M68 -> 0 | O68: 0
H70: =F70/9975360 -> 0 | J70: =H70-M70 -> 0 | O70: 0
O71: 0
H72: =F72/9975360 -> 0 | J72: =H72-M72 -> 0 | O72: 0

Sheet NOTE (4-12)
A2: ='Note 3 (Share Capital)'!A2 -> ABC INDIA LIMITED
A3: Notes to financial statements for the year ended at 31st March 2025
A5: Note 4 | B5: RESERVES AND SURPLUS
B7: Particulars | E7: ='BS PnL'!F8 -> As at March 31, 2025 | F7: ='BS PnL'!G8 -> As at March 31, 2024
B9: Surplus/(Deficit) in Statement of Profit & Loss
B10: Opening balance | E10: =F14 -> 1.3899663e+08 | F10: 80457756
B11: (+) Net Profit/(Loss) For the current year | E11: ='BS PnL'!F109 -> 61436985 | F11: 58538617
B12: (-) Transfer from Reserves* | E12: 83128000 | F12: 0
B13: (+/-) Adjustment to Reserves | E13: 0 | F13: 259
E14: =E10+E11-E12 -> 1.1730562e+08 | F14: =SUM(F10:F13) -> 1.3899663e+08
B15: (+) Securities Premium Reserve | E15: ='[1]Branch Wise 30.09.2024'!$U$145 -> 3314240 | F15: 3314240
B16: Closing Balance | E16: =E10+E11-E12+E15 -> 1.2061986e+08 | F16: =F14+F15 -> 1.4231087e+08
A18: Note 5 | B18: LONG TERM BORROWINGS
B20: Particulars | E20: =E7 -> As at March 31, 2025 | F20: =F7 -> As at March 31, 2024
B22: SECURED
B23: Loan From Other than Related Party
B24: - From Banks | E24: =Borrowing!E10 -> 0 | F24: 119575580
B26: UNSECURED
B27: Loan From Other than Related Party
B28: - From Banks | E28: =Borrowing!E14 -> 0 | F28: 9652174
B29: - From NBFCs | E29: =Borrowing!E18 -> 0 | F29: 4054405
B30: Total | E30: =SUM(E24:E29) -> 0 | F30: =SUM(F23:F29) -> 1.3328216e+08
B31: Refer note no. 45
A33: Note 6 | B33: DEFERRED TAX LIABILITIES/(ASSETS)
B35: Particulars | D35: As at March 31, 2024 | E35: Recognised in Profit or Loss | F35: As at March 31, 2025
B36: Differece in carrying value & tax base of Plant, Property & Equipment | D36: =F41 -> 8026728.4 | E36: 224000.15 | F36: =D36+E36 -> 8250728.5
B37: Gratuity | D37: =F42 -> -354127.1 | E37: 690523.75 | F37: =D37+E37 -> 336396.65
B38: Total | D38: =SUM(D36:D37) -> 7672601.3 | E38: =SUM(E36:E37) -> 914523.89 | F38: =SUM(F36:F37) -> 8587125.1
B40: Particulars | D40: As at March 31, 2023 | E40: Recognised in Profit or Loss | F40: As at March 31, 2024
B41: Differece in carrying value & tax base of Plant, Property & Equipment | D41: 6112077 | E41: 1914651.4 | F41: =D41+E41 -> 8026728.4
B42: Gratuity | D42: 0 | E42: -354127.1 | F42: =D42+E42 -> -354127.1
B43: Total | D43: =SUM(D41:D42) -> 6112077 | E43: =SUM(E41:E42) -> 1560524.3 | F43: =SUM(F41:F42) -> 7672601.3
A45: Note 7 | B45: OTHER LONG TERM LIABILITIES
B47: Particulars | E47: =+E20 -> As at March 31, 2025 | F47: =+F20 -> As at March 31, 2024
B49: Total | E49: =SUM(E48) -> 0 | F49: =SUM(F48) -> 0
A51: Note 7 | B51: LONG TERM PROVISIONS
B53: Particulars | E53: =+E47 -> As at March 31, 2025 | F53: =+F47 -> As at March 31, 2024
B54: Provisions for Gratuity | E54: 2585438 | F54: 1293445
B55: Total | E55: =SUM(E54) -> 2585438 | F55: =SUM(F54) -> 1293445
A57: Note 8 | B57: SHORT TERM BORROWINGS
B59: Particulars | E59: =$E$47 -> As at March 31, 2025 | F59: =$F$47 -> As at March 31, 2024
B61: SECURED
B62: Loan from other than Related party
B63: - From Banks | E63: =Borrowing!F10 -> 0 | F63: 19972515
B64: Loans repayable on demand from bank (cash credit)- Secured | E64: =Borrowing!F26 -> 0 | F64: 1.5422526e+08
B66: UNSECURED
B67: Loan from other than Related party
B68: - From Banks | E68: =Borrowing!F14 -> 0 | F68: 14524629
B69: - From NBFCs | E69: =Borrowing!F18 -> 0 | F69: 3852936.9
B70: Loans repayable on demand from NBFC | E70: =Borrowing!F32 -> 0 | F70: 8160628
B71: Total | E71: =SUM(E62:E70) -> 0 | F71: =SUM(F63:F70) -> 2.0073596e+08
B72: Refer note no. 45
A74: Note 9 | B74: TRADE PAYABLE
B76: Particulars | G76: As at March 31, 2025
B78: Particulars | C78: Less than 1 Year | D78: 1-2 Years | E78: 2-3 Years | F78: More than 3 Years
B79: (i) Un Disputed dues -------
B80: MSME | C80: 76596297 | D80: 0 | E80: 0 | F80: 0 | G80: =SUM(C80:F80) -> 76596297
B81: Others | C81: 19455514 | D81: 0 | E81: 0 | F81: 0 | G81: =SUM(C81:F81) -> 19455514
B82: (ii) Disputed dues ------- | C82: 0 | D82: 0 | E82: 0 | F82: 0 | G82: =SUM(C82:F82) -> 0
B83: MSME | C83: 0 | D83: 0 | E83: 0 | F83: ='[1]Annexure-1'!$E$35 -> 1065039.1 | G83: =SUM(C83:F83) -> 1065039.1
B84: Others | C84: 0 | D84: 0 | E84: 0 | F84: 0 | G84: =SUM(C84:F84) -> 0
B85: Total | C85: =SUM(C79:C84) -> 96051811 | D85: =SUM(D79:D84) -> 0 | E85: =SUM(E79:E84) -> 0 | F85: =SUM(F79:F84) -> 1065039.1 | G85: =SUM(G79:H84) -> 97116850
B87: Particulars | G87: As at March 31, 2024
B89: Particulars | C89: Less than 1 Year | D89: 1-2 Years | E89: 2-3 Years | F89: More than 3 Years
B90: (i) Un Disputed dues -------
B91: MSME | C91: 58628278 | D91: 0 | E91: 0 | F91: 0 | G91: =SUM(C91:F91) -> 58628278
B92: Others | C92: 20765257 | D92: 1425667 | E92: 0 | F92: 0 | G92: =SUM(C92:F92) -> 22190924
B93: (ii) Disputed dues ------- | C93: 0 | D93: 0 | E93: 0 | F93: 0 | G93: =SUM(C93:F93) -> 0
B94: MSME | C94: 0 | D94: 0 | E94: 1065039 | F94: 0 | G94: =SUM(C94:F94) -> 1065039
B95: Others | C95: 0 | D95: 0 | E95: 0 | F95: 0 | G95: =SUM(C95:F95) -> 0
B96: Total | C96: =SUM(C91:C95) -> 79393535 | D96: =SUM(D91:D95) -> 1425667 | E96: =SUM(E91:E95) -> 1065039 | F96: =SUM(F91:F95) -> 0 | G96: =SUM(G91:H95) -> 81884241
B97: * Trade Payable include payable to related party Rs. 1,34,97,237 (P.Y. Rs. 43,56,174)
A99: Note 10 | B99: OTHER CURRENT LIABILITIES
B101: Particulars | E101: =$E$59 -> As at March 31, 2025 | F101: =$F$59 -> As at March 31, 2024
B102: Advance From Customers | E102: ='[2]All Branches Combined'!$O$270 -> 15609433 | F102: 33124884
B103: Security Deposit | E103: ='[2]All Branches Combined'!$O$271 -> 141105 | F103: 245216
B104: Employee benefits and other dues payable | E104: ='[2]All Branches Combined'!$O$274 -> 7143392.7 | F104: 7836675.8
B105: Directors Remuneration Payable | F105: 0
B106: Duties and Taxes
B107: - TDS & TCS Payable | E107: 1809168 | F107: 1381113
B108: - GST Payable | E108: ='[2]All Branches Combined'!$O$273 -> 12790570 | F108: 22450135
B109: - Provident Fund | E109: ='[2]All Branches Combined'!$O$277+'[2]All Branches Combined'!$O$278 -> 384554 | F109: 1009701
B110: Expenses Payable | E110: 21897610 | F110: 7508815.6
B111: Professional Fee Payable | E111: 740884 | F111: 205510
B112: Total | E112: =SUM(E102:E111) -> 60516717 | F112: =SUM(F102:F111) -> 73762051
A114: Note 11 | B114: SHORT TERM PROVISIONS
B116: Particulars | E116: =$E$59 -> As at March 31, 2025 | F116: =$F$59 -> As at March 31, 2024
B117: Provision for Income Tax | E117: =18282862+1071270+623793+3971420 -> 23949345 | F117: 16559164
B118: Provision for Audit Fees | E118: 450000 | F118: 270000
B119: =B54 -> Provisions for Gratuity | E119: 715501 | F119: 113608
B120: Total | E120: =SUM(E117:E119) -> 25114846 | F120: =SUM(F117:F119) -> 16942772

Sheet Note 12 (PPE)
A1: ='BS PnL'!A2 -> ABC INDIA LIMITED
A2: ='NOTE (4-12)'!A3:H3 -> Notes to financial statements for the year ended at 31st March 2025
A4: Note 12: PROPERTY, PLANT AND EQUIPMENT AND INTANGIBLE ASSETS
A6: PARTICULARS | B6: GROSS BLOCK | F6: DEPRECIATION BLOCK | J6: NET BLOCK
B7: COST AS | C7: ADDITION | D7: DELETION | E7: TOTAL | F7: UPTO | G7: DURING | H7: ADJUSTMENT | I7: TOTAL | J7: WDV AS | K7: WDV AS
B8: ON 01.04.2024 | E8: 31.03.2025 | F8: 31.03.2024 | G8: THE YEAR | J8: ON 31.03.2025 | K8: ON 31.03.2024
A10: A. Tangible Assets
A12: Plant & Machinery | B12: 91693612 | C12: 21798952 | D12: 0 | E12: =B12+C12-D12 -> 1.1349256e+08 | F12: =28409389.4621273+242760-1203 -> 28650946 | G12: 7315765.1 | H12: 0 | I12: =F12+G12-H12 -> 35966712 | J12: =E12-I12 -> 77525852 | K12: 60816471
A13: Furniture & Fittings | B13: 1023483 | C13: 2056824.6 | D13: 0 | E13: =B13+C13-D13 -> 3080307.5 | F13: 646471.97 | G13: 84455.992 | H13: 0 | I13: =F13+G13-H13 -> 730927.96 | J13: =E13-I13 -> 2349379.6 | K13: 387789.6
A14: Buildings | B14: 1.7209169e+08 | C14: 0 | D14: 0 | E14: =B14+C14-D14 -> 1.7209169e+08 | F14: 10575724 | G14: 5455306.6 | H14: 0 | I14: =F14+G14-H14 -> 16031031 | J14: =E14-I14 -> 1.5606066e+08 | K14: 1.6151597e+08
A15: Office Equipments | B15: 2763306.3 | C15: 417741.28 | D15: 0 | E15: =B15+C15-D15 -> 3181047.6 | F15: 1394739.5 | G15: 550030.08 | H15: 0 | I15: =F15+G15-H15 -> 1944769.6 | J15: =E15-I15 -> 1236278 | K15: 3895510.9
A16: Computers | B16: 3637603.8 | C16: 605519.66 | D16: 0 | E16: =B16+C16-D16 -> 4243123.4 | F16: 2462745 | G16: 825876.86 | H16: 0 | I16: =F16+G16-H16 -> 3288621.8 | J16: =E16-I16 -> 954501.62 | K16: 1319328.1
A17: Vehicles | B17: 14498182 | C17: 3801727.1 | D17: 0 | E17: =B17+C17+D17 -> 18299909 | F17: 5177363 | G17: 1590908.4 | H17: 0 | I17: =F17+G17+H17 -> 6768271.4 | J17: =E17-I17 -> 11531637 | K17: 9107584.2
A20: Total (A) | B20: =SUM(B12:B17) -> 2.8570788e+08 | C20: =SUM(C12:C17) -> 28680764 | D20: =SUM(D12:D17) -> 0 | E20: =SUM(E12:E17) -> 3.1438864e+08 | F20: =SUM(F12:F17) -> 48907990 | G20: =SUM(G12:G17) -> 15822343 | H20: =SUM(H12:H17) -> 0 | I20: =SUM(I12:I17) -> 64730333 | ... K20: =SUM(K12:K17) -> 2.3704265e+08
A21: Previous Year
A23: B. Intangible Assets
A25: Software | B25: 962699.35 | E25: =B25+C25-D25 -> 962699.35 | F25: 632348.27 | G25: 76964.372 | H25: 0 | I25: =F25+G25-H25 -> 709312.64 | J25: =E25-I25 -> 253386.71 | K25: 330351.08
A26: Patent | B26: 204000 | E26: =B26+C26-D26 -> 204000 | F26: 193800 | G26: 0 | H26: 0 | I26: =F26+G26-H26 -> 193800 | J26: =E26-I26 -> 10200 | K26: =B26-F26 -> 10200
A28: Total (B) | B28: =SUM(B25:B27) -> 1166699.4 | C28: 0 | D28: =SUM(D25:D27) -> 0 | E28: =SUM(E25:E27) -> 1166699.4 | F28: =SUM(F25:F27) -> 826148.27 | G28: =SUM(G25:G27) -> 76964.372 | H28: =SUM(H25:H27) -> 0 | I28: =SUM(I25:I27) -> 903112.64 | J28: =SUM(J25:J27) -> 263586.71 | K28: =SUM(K25:K27) -> 340551.08
A29: Previous Year
A31: C. Freehold Land | B31: 5389290 | D31: 0 | E31: =B31+C31-D31 -> 5389290 | F31: 0 | G31: 0 | H31: 0 | I31: 0 | J31: =+E31-I31 -> 5389290 | K31: =+B31-F31 -> 5389290
A33: Total (C) | B33: =B31 -> 5389290 | C33: =C31 -> 0 | D33: =D31 -> 0 | E33: =E31 -> 5389290 | F33: =F31 -> 0 | G33: =G31 -> 0 | H33: =H31 -> 0 | I33: =I31 -> 0 | ... K33: =K31 -> 5389290
A34: Previous Year
A36: Total : (A+B+C) | B36: =B20+B28+B33 -> 2.9226387e+08 | C36: =C20+C28+C33 -> 28680764 | D36: =D20+D28+D33 -> 0 | E36: =E20+E28+E33 -> 3.2094463e+08 | F36: =F20+F28+F33 -> 49734138 | G36: =G20+G28+G33 -> 15899307 | H36: =H20+H28+H33 -> 0 | I36: =I20+I28+I33 -> 65633446 | ... K36: =K20+K28+K33 -> 2.4277249e+08
A37: Previous Year
B38: 30991
A39: Notes:-
A40: Revaluation of its Property, Plant and Equipment :
A41: The company has not revalued any of its Property, Plant and Equipment for the FY 2024-25. (P.Y. Nil)
G44: =+G36-'BS PnL'!F102 -> 15899307 | J44: =+J36-'BS PnL'!F38-'BS PnL'!F39 -> -1.4668331e-08
J45: 63280390

Sheet 13.CWIP
B2: =+EBP!A1 -> ABC INDIA LIMITED
B3: Notes to Financial Statements for the year ended at March 31, 2025
B5: Note 13: Capital Work In Progress
C7: NET BLOCK
B8: PARTICULARS | C8: COST AS | D8: ADDITION | E8: DELETION | F8: TOTAL | G8: TOTAL
C9: ON 01.04.2024 | F9: 31.03.2025 | G9: 31.03.2024
B11: Capital Work In Progress-Computer Software | C11: =F15 -> 935397.77 | D11: 0 | E11: 0 | F11: =+C11+D11-E11 -> 935397.77 | G11: 935397.77
B12: Capital Work In Progress-Gabion Wall | C12: 0 | D12: 566712 | F12: =+C12+D12-E12 -> 566712
B13: Capital Work In Progress-Water Tank | C13: 0 | D13: 661123.82 | F13: =+C13+D13-E13 -> 661123.82
B14: Total | C14: =SUM(C11) -> 935397.77 | D14: =SUM(D11:D13) -> 1227835.8 | E14: =SUM(E11:E13) -> 0 | F14: =SUM(F11:F13) -> 2163233.6 | G14: =SUM(G11) -> 935397.77
B15: P.Y | C15: 0 | D15: 935397.77 | E15: 0 | F15: 935397.77 | G15: 0
B17: Capital work-in-progress aging schedule
B18: CWIP | C18: Amount in CWIP for the period of
C19: Less than 1 year | D19: 1-2 years | E19: 2-3 years | F19: More than 3 years | G19: Total
B20: As at 31st March 2025
B21: Projects in Progress | C21: =F12+F13 -> 1227835.8 | D21: =F11 -> 935397.77 | E21: 0 | F21: 0 | G21: =SUM(C21:F21) -> 2163233.6
B22: Projects Temporarily suspended | C22: 0 | D22: 0 | E22: 0 | F22: 0 | G22: 0
B24: CWIP | C24: Amount in CWIP for the period of
C25: Less than 1 year | D25: 1-2 years | E25: 2-3 years | F25: More than 3 years | G25: Total
B26: As at 31st March 2024
B27: Projects in Progress | C27: 935398 | D27: 0 | E27: 0 | F27: 0 | G27: =SUM(C27:F27) -> 935398
B28: Projects Temporarily suspended | C28: 0 | D28: 0 | E28: 0 | F28: 0 | G28: 0

Sheet Note (13-20)
A1: ='NOTE (4-12)'!A2:H2 -> ABC INDIA LIMITED
A2: ='NOTE (4-12)'!A3:H3 -> Notes to financial statements for the year ended at 31st March 2025
A4: Note 14 | B4: NON-CURRENT INVESTMENTS
B6: Particulars | F6: ='NOTE (4-12)'!$E$59 -> As at March 31, 2025 | G6: ='NOTE (4-12)'!$F$59 -> As at March 31, 2024
B7: Investments in Government securities
B8: - Sovereign Gold Bond | F8: ='[2]All Branches Combined'!$O$291 -> 51040 | G8: 51040
B10: Investment in Body Corporate
B11: - ABCD Limited (subsidiary)
B12: (19,999 Equity Shares holding 99.995% of total holding) | F12: ='[2]All Branches Combined'!$O$293 -> 1780879.5 | G12: 1780879.5
B13: - ABCDE (subsidiary)
B14: (40,766 Equity Shares holding 74.44% of total holding) | F14: ='[2]All Branches Combined'!$O$292 -> 2548225 | G14: 2548225
B16: Total | F16: =SUM(F8:F14) -> 4380144.5 | G16: =SUM(G8:G14)+1 -> 4380145.5
A18: Note 15 | B18: OTHER NON-CURRENT ASSETS
B20: Particulars | F20: ='NOTE (4-12)'!$E$59 -> As at March 31, 2025 | G20: As at March 31, 2024
B21: FD & DD Deposit for Tenders | F21: 14935655 | G21: 16793070
B22: Office Rent Security and Others | F22: ='[2]All Branches Combined'!$O$317 -> 2262927 | G22: 1216982
B23: Security Deposit with Client and Others | F23: ='[2]All Branches Combined'!$O$312 -> 4102889.8 | G23: 3809468.8
B24: Refund of Sales Tax on GTA | F24: ='[2]All Branches Combined'!$O$321 -> 148148 | G24: 148148
B25: Total | F25: =SUM(F21:F24) -> 21449620 | G25: =SUM(G21:G24) -> 21967669
A27: Note 16 | B27: INVENTORIES
B29: Particulars | F29: ='NOTE (4-12)'!$E$59 -> As at March 31, 2025 | G29: ='NOTE (4-12)'!$F$59 -> As at March 31, 2024
B30: Raw Material | F30: ='[2]All Branches Combined'!$O$296 -> 29404790 | G30: 28412958
B31: WIP | F31: 2735891.4 | G31: 0
B32: Finished Goods | F32: ='[2]All Branches Combined'!$O$297 -> 1.1172809e+08 | G32: 66619242
B33: Stock in Trade | F33: ='[2]All Branches Combined'!$O$299 -> 63556227 | G33: 27724625
B34: Total | F34: =SUM(F30:F33) -> 2.07425e+08 | G34: =SUM(G30:G33) -> 1.2275682e+08
A36: Note 17 | B36: TRADE RECEIVABLE
B38: Particulars | C38: Outstanding for following periods from due date of payment | H38: As at March 31, 2025
C40: Less than 6 Months | D40: More than 6 Months | E40: 1-2 Years | F40: 2-3 Years | G40: More than 3 Years
B41: (i) Trade Receivable - Considered Good | C41: 1.6260844e+08 | D41: 34450432 | E41: 13521387 | F41: 674128.71 | G41: 12716253 | H41: =SUM(C41:G41) -> 2.2397064e+08
B42: (i) Trade Receivable - Doubtful | C42: 0 | D42: 0 | E42: 0 | F42: 0 | G42: 0 | H42: =SUM(C42:G42) -> 0
B43: (iii) Disputed trades -------
B44: Trade Receivable - Considered Good | C44: 4219761 | D44: 0 | E44: 2068224 | F44: 23195606 | G44: 0 | H44: =SUM(C44:G44) -> 29483591
B45: Trade Receivable - Doubtful | C45: 0 | D45: 0 | E45: 0 | F45: 0 | G45: 0 | H45: =SUM(C45:G45) -> 0
B46: Total | C46: =SUM(C41:C45) -> 1.668282e+08 | D46: =SUM(D41:D45) -> 34450432 | E46: =SUM(E41:E45) -> 15589611 | F46: =SUM(F41:F45) -> 23869735 | G46: =SUM(G41:G45) -> 12716253 | H46: =SUM(H41:H45) -> 2.5345423e+08
B48: Particulars | C48: Outstanding for following periods from due date of payment | H48: As at March 31, 2024
C50: Less than 6 Months | D50: More than 6 Months | E50: 1-2 Years | F50: 2-3 Years | G50: More than 3 Years
B51: (i) Trade Receivable - Considered Good | C51: 153682395 | D51: 23341410 | E51: 23397162 | F51: 7662560 | G51: 0 | H51: =SUM(C51:G51) -> 208083527
B52: (i) Trade Receivable - Doubtful | C52: 0 | D52: 0 | E52: 0 | F52: 0 | G52: 0 | H52: =SUM(C52:G52) -> 0
B53: (iii) Disputed trades ------- | H53: =SUM(C53:G53) -> 0
B54: Trade Receivable - Considered Good | C54: 0 | D54: 0 | E54: 0 | F54: 0 | G54: 0 | H54: =SUM(C54:G54) -> 0
B55: Trade Receivable - Doubtful | C55: 0 | D55: 0 | E55: 0 | F55: 0 | G55: 0 | H55: =SUM(C55:G55) -> 0
B56: Total | C56: =SUM(C51:C55) -> 153682395 | D56: =SUM(D51:D55) -> 23341410 | E56: =SUM(E51:E55) -> 23397162 | F56: =SUM(F51:F55) -> 7662560 | G56: =SUM(G51:G55) -> 0 | H56: =SUM(H51:H55) -> 208083527
A58: Note 18 | B58: CASH & CASH EQUIVALENTS
B60: =B6 -> Particulars | F60: =F6 -> As at March 31, 2025 | G60: =G6 -> As at March 31, 2024
B61: Balances with Banks | F61: ='[2]All Branches Combined'!$O$307 -> 600 | G61: 25096.55
B62: Cash in hand | F62: ='[2]All Branches Combined'!$O$308 -> 43816 | G62: 23193
B63: Total | F63: =SUM(F61:F62) -> 44416 | G63: =SUM(G61:G62) -> 48289.55
A65: Note 19 | B65: SHORT TERM LOANS & ADVANCES
B67: =$B$60 -> Particulars | F67: =$F$60 -> As at March 31, 2025 | G67: =$G$60 -> As at March 31, 2024
B68: Advance to Supplier | F68: ='[2]All Branches Combined'!$O$318+'[2]All Branches Combined'!$O$324-F69+24 -> 14820820 | G68: =29795116.5-G69 -> 7446248.5
B69: Retention Money | F69: 32270745 | G69: =22348868 -> 22348868
B70: Staff Imprest Expense | F70: ='[2]All Branches Combined'!$O$331 -> 93808.57 | G70: 1708455.1
B71: Loan and Advance to Related Party (Unsecured) | F71: ='[2]All Branches Combined'!$O$319 -> 9549877.8 | G71: 5852359.5
B72: Total | F72: =SUM(F68:F71)+0.01 -> 56735251 | G72: =SUM(G68:G71)+10 -> 37355941
B74: *Loan & Advances to Related Party
B75: Particulars | C75: As at March 31, 2025 | D75: % of Total Amount | E75: As at March 31, 2024 | F75: % of Total Amount
B77: Common Control Entity | C77: =+F71 -> 9549877.8 | D77: =C77/C78*100 -> 100 | E77: =+G71 -> 5852359.5 | F77: =E77/E78*100 -> 100
B78: Total | C78: =SUM(C77) -> 9549877.8 | D78: =SUM(D77:D77) -> 100 | E78: =E77 -> 5852359.5 | F78: =F77 -> 100
A80: Note 20 | B80: OTHER CURRENT ASSETS
B82: =$B$60 -> Particulars | F82: =$F$60 -> As at March 31, 2025 | G82: =$G$60 -> As at March 31, 2024
B83: FD & DD Deposit for Tenders | F83: =21768914.8-F84 -> 6594002 | G83: =17465890-G84 -> 11434398
B84: Earnest Money Deposit | F84: 15174913 | G84: 6031491.8
B85: Prepaid Expenses | F85: ='[2]All Branches Combined'!$O$315 -> 1785094.1 | G85: 844067.75
B86: Balance with Revenue Authorities | F86: ='[2]All Branches Combined'!$O$314+'[2]All Branches Combined'!$O$320+'[2]All Branches Combined'!$O$322+'[2]All Branches Combined'!$O$34 -> 16523010 | G86: 16700496
B87: Interest Receivable | F87: ='[2]All Branches Combined'!$O$316 -> 2234985.2 | G87: 1198959.8
B88: Total | F88: =SUM(F83:F87)+0.01 -> 42312004 | G88: =SUM(G83:G87)+0.01 -> 36209414

Sheet Note 20-31
A1: ='Note (13-20)'!A1 -> ABC INDIA LIMITED
A2: ='Note (13-20)'!A2 -> Notes to financial statements for the year ended at 31st March 2025
A4: Note 21 | B4: REVENUE FROM OPERATIONS
B6: Particulars | C6: =$C$15 -> For the period ended at March 31, 2025 | D6: =$D$15 -> For the period ended at March 31, 2024
B7: Sale of Products
B8: -Export | C8: ='[3]All Branches Combined'!$O$333 -> 8355400 | D8: 11905200
B9: -Domestic | C9: ='[3]All Branches Combined'!$O$334 -> 6.563224e+08 | D9: 6.7639928e+08
B10: Sale of Services | C10: ='[3]All Branches Combined'!$O$335 -> 3.3617098e+08 | D10: 3.5821898e+08 | XFD10: =+XEY11-XEY31-XEY30+XEY33-XEY41-XEY53+XEY59 -> 0
B11: Total (A+B+C) | C11: =SUM(C8:C10) -> 1.0008488e+09 | D11: =SUM(D8:D10) -> 1.0465235e+09
A13: Note 22 | B13: OTHER INCOME
B15: Particulars | C15: =C64 -> For the period ended at March 31, 2025 | D15: =D64 -> For the period ended at March 31, 2024
B16: Interest on Deposits | C16: ='[2]All Branches Combined'!$O$340-C17 -> 1600385.7 | D16: 896209
B17: Interest on Inter-corporate Loan | C17: 515168.27 | D17: 690108
B18: Insurance Claim | C18: ='[2]All Branches Combined'!$O$344 -> 119598 | D18: 428773
B19: Profit on Sale of PPE
B20: Foreign Exchange Difference | C20: ='[2]All Branches Combined'!$O$341 -> 96369.05 | D20: 0
B21: Balances Written off | C21: ='[2]All Branches Combined'!$O$342 -> 6701597.4 | D21: 1152
B22: Miscellaneous Income | C22: ='[2]All Branches Combined'!$O$343 -> 594 | D22: 0
B23: Total | C23: =SUM(C16:C22) -> 9033712.5 | D23: =SUM(D16:D22) -> 2016242
A25: Note 23 | B25: COST OF MATERIAL CONSUMED
B27: Particulars | C27: =C15 -> For the period ended at March 31, 2025 | D27: =D15 -> For the period ended at March 31, 2024
B29: RAW MATERIAL CONSUMED
B30: Stock at the beginning of the year | C30: =D33 -> 28412958 | D30: 17970513
B31: Add: Purchases | C31: ='[2]All Branches Combined'!$O$350 -> 3.7007346e+08 | D31: 5.0668915e+08
B32: Cost of Goods Available for Consumption | C32: =SUM(C30:C31) -> 3.9848642e+08 | D32: =SUM(D30:D31) -> 5.2465967e+08
B33: Less: Stock at the end of the year | C33: ='Note (13-20)'!F30 -> 29404790 | D33: 28412958
B34: Total | C34: =+C32-C33 -> 3.6908163e+08 | D34: =+D32-D33 -> 4.9624671e+08
A37: Note 24 | B37: PURCHASE STOCK IN TRADE
B39: Particulars | C39: =C27 -> For the period ended at March 31, 2025 | D39: =D27 -> For the period ended at March 31, 2024
B41: Purchase of Goods Traded | C41: ='[2]All Branches Combined'!$O$357 -> 1.7776843e+08 | D41: 95333036
B42: Total | C42: =C41 -> 1.7776843e+08 | D42: =D41 -> 95333036
B43: * Purchase form related party Rs. 6,70,56,487 (PY Rs. 6,09,94,089)
A45: Note 25 | B45: CHANGES IN INVENTORIES OF STOCK IN TRADE AND FINISHED GOODS
B47: Particulars | C47: =C39 -> For the period ended at March 31, 2025 | D47: =D39 -> For the period ended at March 31, 2024
B49: Inventories at the beginning of the year:
B50: Stock In Trade | C50: =D56 -> 27724625 | D50: 21799534
B51: WIP | C51: 0 | D51: 0
B52: Finished goods | C52: =D58 -> 66619242 | D52: 36039168
B53: Total inventories at the beginning of the year | C53: =SUM(C50:C52) -> 94343867 | D53: =D50+D52 -> 57838701
B55: Inventories at the end of the year:
B56: Stock In Trade | C56: ='Note (13-20)'!F33 -> 63556227 | D56: 27724625
B57: WIP | C57: 2735891.4 | D57: 0
B58: Finished goods | C58: ='Note (13-20)'!F32 -> 1.1172809e+08 | D58: 66619242
B59: Total inventories at the end of the year | C59: =SUM(C56:C58) -> 1.7802021e+08 | D59: =SUM(D56:D58) -> 94343867
B60: Change in Inventory | C60: =C53-C59 -> -83676346 | D60: =D53-D59 -> -36505165
A62: Note 26 | B62: EMPLOYEE BENEFITS EXPENSE
B64: Particulars | C64: For the period ended at March 31, 2025 | D64: For the period ended at March 31, 2024
B66: Salary and Wages | C66: ='[2]All Branches Combined'!$O$360 -> 107266305 | D66: =95533326.87-D68 -> 94126274
B67: Contribution to Provident Fund and Other Funds | C67: ='[2]All Branches Combined'!$O$361+'[2]All Branches Combined'!$O$362-C68 -> 3099572.2 | D67: 2214434
B68: Gratuity Expenses | C68: ='[2]Branch Wise 31.03.2025'!$T$357 -> 1603432 | D68: 1407053
B69: Director Remuneration | C69: ='[2]All Branches Combined'!$O$363 -> 8000000 | D69: 4064000
B70: Staff Welfare and Expenses | C70: ='[2]All Branches Combined'!$O$365 -> 6997977 | D70: 569014.85
B71: Total | C71: =SUM(C66:C70) -> 1.2696729e+08 | D71: =SUM(D66:D70) -> 1.0238078e+08
A73: Note 27 | B73: OTHER EXPENSES
B75: Particulars | C75: For the period ended at March 31, 2025 | D75: For the period ended at March 31, 2024 | H75: Business Promotion | I75: ='[2]All Branches Combined'!$O$383 -> 1753759.8
H76: Conveyance Exp. | I76: ='[2]All Branches Combined'!$O$384 -> 240477.8
B77: Audit Remuneration* | C77: 500000 | D77: 300000 | H77: Fee & Subscription | I77: ='[2]All Branches Combined'!$O$385 -> 1236697.7
B78: Commission Expenses | C78: ='[2]All Branches Combined'!$O$409 -> 7873099 | D78: 4463385 | H78: Production Expenses | I78: ='[2]All Branches Combined'!$O$389 -> 456734.5
B79: Liquidated Damages | H79: Office expenses | I79: ='[2]All Branches Combined'!$O$393 -> 2914411
B80: Foreign Exchange Fluctuation Loss | H80: Interest to Other | I80: ='[2]All Branches Combined'!$O$395 -> 805604
B81: Freight and Forwarding charges | C81: ='[2]All Branches Combined'!$O$387 -> 61010423 | D81: 61931148 | H81: Miscellanoues Expenses | I81: ='[2]All Branches Combined'!$O$398 -> 3684187.4
B82: Installation and Job Work Expenses | C82: ='[2]All Branches Combined'!$O$388 -> 49113870 | D82: 55700376 | H82: Postage & Courier | I82: ='[2]All Branches Combined'!$O$401 -> 730166.07
B83: Insurance Expenses | C83: ='[2]All Branches Combined'!$O$394 -> 907217.3 | D83: 1016237 | H83: Printing & Stationery | I83: ='[2]All Branches Combined'!$O$403 -> 320209.76
B84: Legal & professional Expenses | C84: ='[2]All Branches Combined'!$O$396 -> 3168003.4 | D84: 2156764 | H84: Telephone & Internet Exp. | I84: ='[2]All Branches Combined'!$O$407 -> 366639.17
B85: Miscellanoues Expenses | C85: =I100 -> 25283116 | D85: 15079304 | H85: Testing Charges | I85: ='[2]All Branches Combined'!$O$408 -> 1672259.1
B86: Power and Fuel | C86: ='[2]All Branches Combined'!$O$399+'[2]All Branches Combined'!$O$400 -> 19035770 | D86: 19310963 | H86: Vehicle Running Charges | I86: ='[2]All Branches Combined'!$O$411 -> 813636.42
B87: Rates and Taxes | C87: ='[2]All Branches Combined'!$O$404 -> 7264003.4 | D87: 7838787 | H87: Round Off | I87: ='[2]All Branches Combined'!$O$416 -> 730.4
B88: Rent Expenses | C88: ='[2]All Branches Combined'!$O$391 -> 24807034 | D88: 32838313 | H88: Clearing & Forwarding Expenses | I88: ='[2]All Branches Combined'!$O$390 -> 3680125.1
B89: Repair & Maintinance Expenses | C89: ='[2]All Branches Combined'!$O$405 -> 5655012.4 | D89: 4396763 | H89: Loading & Unloading Exp. | I89: ='[2]All Branches Combined'!$O$397 -> 974833.08
B90: Site Expenses | C90: ='[2]All Branches Combined'!$O$406+'[2]All Branches Combined'!$O$414 -> 51044900 | D90: 47836443 | H90: Electricity Expense | I90: ='[2]All Branches Combined'!$O$386 -> 3340970.4
B91: Tour & Travelling Expenses | C91: ='[2]All Branches Combined'!$O$410 -> 13808947 | D91: 10987554 | H91: CSR Expense | I91: ='[2]All Branches Combined'!$O$392 -> 1050000
B92: Prior Period Items | C92: 0 | D92: 0
B93: Total | C93: =SUM(C77:C92) -> 2.694714e+08 | D93: =SUM(D77:D92) -> 2.6385604e+08 | H93: ROC Expense | I93: ='[2]All Branches Combined'!$O$412 -> 1212210.1
H95: IPO Expense | I95: ='[2]All Branches Combined'!$O$413 -> 52838
B98: * Payments to the auditor as: | H98: Boulder Expense | I98: 0
B99: As Auditor: | H99: Prior period Expense | I99: =-23648.52+275 -> -23373.52
B100: - Statutory Audit | C100: 450000 | D100: 180000 | I100: =SUM(I75:I99) -> 25283116
B101: - Tax Audit | C101: 50000 | D101: 60000
B102: - GST Audit | C102: 0 | D102: 60000
B103: Total | C103: =SUM(C100:C102) -> 500000 | D103: =SUM(D100:D102) -> 300000
A105: Note 28 | B105: FINANCE COST
B107: Particulars | C107: For the period ended at March 31, 2025 | D107: For the period ended at March 31, 2024
B109: Processing Fees | C109: ='[2]All Branches Combined'!$O$370 -> 2087002.6 | D109: 2710856.5
B110: Interest on Vehicle Loan & Machinery | C110: ='[2]All Branches Combined'!$O$374+'[2]All Branches Combined'!$O$375 -> 2060862.7 | D110: 1652130.3
B111: Bank Interest on Overdraft | C111: ='[2]All Branches Combined'!$O$371 -> 19202875 | D111: 11423852
B112: Interest on Term Loan | C112: ='[2]All Branches Combined'!$O$372+'[2]All Branches Combined'!$O$373+'[2]All Branches Combined'!$O$376 -> 16922732 | D112: 20118891
B113: Interest on MSME Dues | C113: ='[2]Branch Wise 31.03.2025'!$U$372 -> 818207.52 | D113: 0
B114: Interest over late payment of Income taxes & TDS | C114: ='[2]Branch Wise 31.03.2025'!$U$373 -> 1695063 | D114: 0
B115: Bank Charges | C115: ='[2]All Branches Combined'!$O$369 -> 1502102.4 | D115: 446022.08
B116: Total | C116: =SUM(C109:C115)+0.01 -> 44288846 | D116: =SUM(D109:D115) -> 36351752
A119: Note 29 | B119: CURRENT TAX
B121: Particulars | C121: For the period ended at March 31, 2025 | D121: For the period ended at March 31, 2024
B123: Income Tax Expense | C123: 23733634 | D123: 16559164
B124: Total | C124: =SUM(C123:C123) -> 23733634 | D124: =SUM(D123:D123) -> 16559164
A127: Note 30 | B127: Earning Per Share
B129: ='Note 20-31'!B64 -> Particulars | C129: For the period ended at March 31, 2025 | D129: ='Note 20-31'!$D$75 -> For the period ended at March 31, 2024
B132: Basic & Diluted Earnings per Share (Rs)
B133: Profit/(Loss) after tax as per Profit & Loss account (Rs) | C133: ='BS PnL'!F109 -> 61436985 | D133: ='BS PnL'!G109 -> 58538635
B134: Number of Equity Shares as at beginning of the year | C134: ='Note 3 (Share Capital)'!F20 -> 166256 | D134: ='Note 3 (Share Capital)'!J20 -> 166256
B135: Number of Equity Shares as at end of the year | C135: ='Note 3 (Share Capital)'!F23 -> 9975360 | D135: ='Note 3 (Share Capital)'!J23 -> 166256
...

Sheet EBP
A1: ='Note 1-2'!A2 -> ABC INDIA LIMITED
A2: Notes to Financial Statements for the period ended at March 31, 2025
A5: Note 45 | B5: EMPLOYEE BENEFIT PLANS:
A7: A) | B7: Defined Contribution Plans:
B8: The Company makes contribution in the form of provident funds as considered defined contribution plans and contribution to Employees Providend Fund Orgnisation. The Company has no further payment obligations once the contributions have been paid. Following are the schemes covered under defined contributions plans of the Company:
B9: Provident Fund Plan : The Company makes monthly contributions at prescribed rates towards Employee Provident Fund administered and managed by Ministry of Labour & Employment,Government of India.
B10: Employee State Insurance: The Company makes prescribed monthly contributions towards Employees State Insurance Scheme and payment made to Employee State Insurance Corporation, Ministry of Labour & Employment,Government of India.
B11: The Company has charged the following costs in contribution to Provident and Other Funds in the Statement of Profit and Loss:
B12: Particulars | F12: For the year ended
F13: 31st March, 2025 | G13: 31st March, 2024
B14: Company’s contribution to Provident Fund & ESI | F14: ='Note 20-31'!C67 -> 3099572.2 | G14: 2214434
B15: Administrative charges on above fund | F15: 214343 | G15: 165264
F16: =SUM(F14:F15) -> 3313915.2 | G16: =SUM(G14:G15) -> 2379698
A18: B) | B18: Defined Benefit Plans:
A19: (i) | B19: The Company provides for gratuity obligations through a defined benefit retirement plan (the ‘Gratuity Plan’) covering all company employees. The Gratuity Plan provides a lump sum payment to vested employees at retirement termination of employment or death of an employee, based on the respective employees’ salary and years of employment with the Company.
A20: (ii) | B20: Risk exposure
A21: a) | B21: Risk to the beneficiary
B22: The greatest risk to the beneficiary is that there are insufficient funds available to provide the promised benefits. This may be due to: • The insufficient funds set aside, i.e. underfunding • The insolvency of the Employer • The holding of investments which are not matched to the liabilities • A combination of these events
A23: b) | B23: Risk Parameter
B24: Actuarial valuation is done basis some assumptions like salary inflation, discount rate, withdrawal assumptions and mortality rate. In case the actual experience varies from the assumptions, fund may be insufficient to pay off the liabilities. Similarly, reduction in discount rate in subsequent future years can increase the plan's liability. Further, actual withdrawals may be lower or higher then what was assumptions the valuation,may also impact the plan's liability.
A25: c) | B25: Risk of illiquid Assets
B26: Another risk is that the funds, although sufficient, are not available when they are required to finance the benefits.This may be due to assets being locked for longer period or in illiquid assets.
A28: d) | B28: Risk of Benefit Change
B29: There may be a risk that the benefit promised is changed or is changeable within the terms of the contract.
A30: e) | B30: Asset liability mismatching risk
B31: ALM risk arises due to a mismatch between assets and liabilities either due to liquidity or changes in interest rates or due to different duration.
A33: (iii) | B33: Changes in defined benefit obligation
D34: Gratuity
B35: Particulars | D35: For the year ended
D36: 31st March, 2025 | E36: 31st March, 2024
B37: Changes in present value of obligation
B38: Present value of obligation as at beginning of the year | D38: 1964334 | E38: 1440701
B39: Interest cost | D39: 127474 | E39: 95866
B40: Current service cost | D40: 661650 | E40: 675544
B41: Benefits paid | D41: -266827 | E41: -71394
B42: Remeasurement-Actuarial loss/(gain) | D42: 814308 | E42: -176383
B44: Remeasurement gains / (losses) recognised in other comprehensive income:
B45: Actuarial (gain)/ loss arising form
B46: -Changes in financial assumptions | D46: 0 | E46: 0
B47: -Changes in demographic assumptions | D47: 0 | E47: 0
B48: -Changes in experience adjustments | D48: 0 | E48: 0
D49: =SUM(D38:D48) -> 3300939 | E49: =SUM(E38:E48) -> 1964334
D51: Leave Encashment
B52: Particulars | D52: For the year ended
D53: 31st March, 2024 | E53: 31st March, 2023
B54: Changes in present value of obligation
B55: Present value of obligation as at beginning of the year | D55: =E66 -> 0 | E55: 0
B56: Interest cost | D56: 0 | E56: 0
B57: Current service cost | D57: =[4]tB!B207 -> 4703090 | E57: 0
B58: Benefits paid | D58: 0 | E58: 0
B59: Remeasurement-Actuarial loss/(gain) | D59: 0 | E59: 0
B61: Remeasurement gains / (losses) recognised in other comprehensive income:
B62: Actuarial (gain)/ loss arising form
B63: -Changes in financial assumptions | D63: 0 | E63: 0
B64: -Changes in demographic assumptions | D64: 0 | E64: 0
B65: -Changes in experience adjustments | D65: 0 | E65: 0
D66: =SUM(D55:D65) -> 4703090 | E66: =SUM(E55:E65) -> 0
A67: (iv) | B67: Fair Value of Plan Assets
D68: Gratuity
B69: Particulars | D69: For the year ended
D70: 31st March, 2025 | E70: 31st March, 2024
B71: Fair value of plan assets at the beginning of the year | D71: =E80 -> 0 | E71: 0
B72: Expenses recognised in profit and loss account
B73: Expected return on plan assets | D73: 0 | E73: 0
B74: Acturial gain/(loss) | D74: 0 | E74: 0
B76: Contributions by employer directly settled | D76: 0 | E76: 0
B77: Contributions by employer | D77: 0 | E77: 0
B78: Benefit payments | D78: 0 | E78: 0
B80: Fair value of plan assets at the end of the year | D80: =SUM(D71:D79) -> 0 | E80: =SUM(E71:E79) -> 0
D82: Leave Encashment
B83: Particulars | D83: For the year ended
D84: 31st March, 2024 | E84: 31st March, 2023
B85: Fair value of plan assets at the beginning of the year | D85: =E94 -> 0 | E85: 0
B86: Expenses recognised in profit and loss account
B87: Expected return on plan assets | D87: 0 | E87: 0
B88: Acturial gain/(loss) | D88: 0 | E88: 0
B90: Contributions by employer directly settled | D90: 0 | E90: 0
B91: Contributions by employer | D91: 0 | E91: 0
B92: Benefit payments | D92: 0 | E92: 0
B94: Fair value of plan assets at the end of the year | D94: =SUM(D85:D93) -> 0 | E94: =SUM(E85:E93) -> 0
A96: (v) | B96: Amount recognised in Balance Sheet
D97: Gratuity
B98: Particulars | D98: As at 31st March, 2025 | E98: As at 31st March, 2024
B99: Defined benefit obligation at the end of the year | D99: =-D49 -> -3300939 | E99: =-E49 -> -1964334
B100: Fair value of plan assets at the end of the year | D100: =D80 -> 0 | E100: =E80 -> 0
B102: Recognised in the balance sheet | D102: =D99+D100 -> -3300939 | E102: =E99+E100 -> -1964334
B103: Current portion of above | D103: -715501 | E103: -362964
B104: Non Current portion of above | D104: =D102-D103 -> -2585438 | E104: =+E102-E103 -> -1601370
D106: Leave Encashment
B107: Particulars | D107: As at 31st March, 2024 | E107: As at 31st March, 2023
B108: Defined benefit obligation at the end of the year | D108: =D66 -> 4703090 | E108: 0
B109: Fair value of plan assets at the end of the year | D109: =D89 -> 0 | E109: =E89 -> 0
B111: Recognised in the balance sheet | D111: =D108+D109 -> 4703090 | E111: =E108+E109 -> 0
B112: Current portion of above
B113: Non Current portion of above
A116: (vi) | B116: Expense recognised in the Statement of profit & loss
D117: Gratuity
B118: Particulars | D118: For the year ended
D119: 31st March, 2025 | E119: 31st March, 2024
B120: Current service cost | D120: =D40 -> 661650 | E120: =E40 -> 675544
...

Sheet Ratio_working
A1: 1 | B1: Current Ratios | C1: FY | D1: PY
B2: Sum of all CA | C2: =+SUM('BS PnL'!F45:F49) -> 5.599709e+08 | D2: =+SUM('BS PnL'!G45:G49) -> 4.0445399e+08
B3: Sum of all CL | C3: =SUM('BS PnL'!F25:F30) -> 1.8274841e+08 | D3: =SUM('BS PnL'!G25:G30) -> 3.7332503e+08
A5: 2 | B5: Debt Equity Ratio
B6: Long Term Debt | C6: =+'BS PnL'!F19 -> 0 | D6: =+'BS PnL'!G19 -> 1.3328216e+08
B7: Shareholder's Equity | C7: =+SUM('BS PnL'!F13:F14) -> 2.2037346e+08 | D7: =+SUM('BS PnL'!G13:G14) -> 1.5893647e+08
A9: 3 | B9: Debt Service Converge Ratio
B10: Earning Available for Debt Services | C10: =+'BS PnL'!F100-'BS PnL'!F107 -> 66348305 | D10: =+'BS PnL'!G100-'BS PnL'!G107 -> 60099159
B11: Debt Services | C11: =+'NOTE (4-12)'!E24+'NOTE (4-12)'!E28+'NOTE (4-12)'!E29+'NOTE (4-12)'!E63+'NOTE (4-12)'!E68+'NOTE (4-12)'!E69+'Note 20-31'!C110+'Note 20-31'!C111+'Note 20-31'!C112+'NOTE (4-12)'!E64+'NOTE (4-12)'!E70 -> 38186470 | D11: =+'NOTE (4-12)'!F24+'NOTE (4-12)'!F28+'NOTE (4-12)'!F29+'NOTE (4-12)'!F63+'NOTE (4-12)'!F68+'NOTE (4-12)'!F69+'Note 20-31'!D110+'Note 20-31'!D111+'Note 20-31'!D112+'NOTE (4-12)'!F64+'NOTE (4-12)'!F70 -> 3.67213e+08
A14: 3 | B14: Return of Equity Ratio
B15: Net Profit After Tax | C15: =+'BS PnL'!F109 -> 61436985 | D15: =+'BS PnL'!G109 -> 58538635
B16: Avg Shareholder Equity | C16: =+SUM('BS PnL'!F13:G14)/2 -> 1.8965496e+08 | D16: =+SUM('BS PnL'!G13:H14)/2 -> 79468236
A18: 4 | B18: Trade Receivables Turnover Ratio
B19: Revenue from operations | C19: =+'BS PnL'!F83 -> 1.0008488e+09 | D19: =+'BS PnL'!G83 -> 1.0465235e+09
B20: Average Accounts Receivable | C20: =+SUM('BS PnL'!F46:G46)/2 -> 2.3076888e+08 | D20: =+SUM('BS PnL'!G46:H46)/2 -> 1.0404176e+08
A22: 5 | B22: Trade Payables Turnover Ratio
B23: Net Credit Purchases | C23: =+('Note 20-31'!C41+'Note 20-31'!C31) -> 5.478419e+08 | D23: =+('Note 20-31'!D41+'Note 20-31'!D31) -> 6.0202219e+08
B24: Average Trade Payables | C24: {=+SUM('BS PnL'!F27:F28/2)} -> 48558425 | D24: {=+SUM('BS PnL'!G27:G28/2)} -> 40942120
A26: 6 | B26: Working Capital Turnover Ratio | F26: 2025 | G26: 2024
B27: Revenue from operations | C27: =+C19 -> 1.0008488e+09 | D27: =+D19 -> 1.0465235e+09 | E27: CA | F27: =C2 -> 5.599709e+08 | G27: 4.0479828e+08
B28: Avg Working Cpital | C28: =(F29+G29)/2 -> 2.0434787e+08 | D28: 33622163 | E28: CL | F28: =C3 -> 1.8274841e+08 | G28: 3.7332503e+08
E29: WC | F29: =F27-F28 -> 3.7722249e+08 | G29: 31473256
A31: 7 | B31: Net Profit Ratio
B32: Net Profit after Tax | C32: =+C15 -> 61436985 | D32: =+D15 -> 58538635
B33: Net Sales | C33: =+C19 -> 1.0008488e+09 | D33: =+D19 -> 1.0465235e+09
A35: 8 | B35: Return on Capital Employed | D35: 2022
B36: Earnings before Interest and Taxes | C36: =+'BS PnL'!F100-'BS PnL'!F102 -> 90081940 | D36: =+'BS PnL'!G100-'BS PnL'!G102 -> 76658323 | F36: 2025 | G36: 2024
B37: Capital Employed | C37: =F39 -> 6.6052668e+08 | D37: =G39 -> 3.0118468e+08 | E37: TA | F37: =+'BS PnL'!F51 -> 8.4327509e+08 | G37: 6.745097e+08
E38: CL | F38: =F28 -> 1.8274841e+08 | G38: 3.7332503e+08
E39: CE | F39: =F37-F38 -> 6.6052668e+08 | G39: 3.0118468e+08
A40: 9 | B40: Inventory T/O Ratio
B41: Cost Of goods sold | C41: =F42+G42-H42 -> 4.6317372e+08 | D41: =F43+G43-H43 -> 5.5507458e+08 | E41: COGS | F41: Opening | G41: Purchases | H41: Closing
B42: Average Inventory | C42: =(F42+H42)/2 -> 1.6509091e+08 | D42: =(F43+H43)/2 -> 99283019 | E42: 2025 | F42: =+H43 -> 1.2275682e+08 | G42: =C23 -> 5.478419e+08 | H42: =+'Note (13-20)'!F34 -> 2.07425e+08
E43: 2024 | F43: 75809214 | G43: 6.0202219e+08 | H43: 1.2275682e+08

Sheet Other Notes
A1: =+'Note 20-31'!A1 -> ABC INDIA LIMITED
A2: =+'Note 20-31'!A2 -> Notes to financial statements for the year ended at 31st March 2025
A6: Note 32 | B6: Disclosures Required Under Section 22 of The Micro, Small and Medium Enterprises Development Act, 2006
B8: Particulars | E8: 31st March, 2025 | F8: 31st March, 2024
B9: The principle amount and the interest due thereon remaining unpaid to any supplier at the end of each accounting year;
B10: (i) Principal Amount | E10: =+'BS PnL'!F27 -> 77661336 | F10: =+'BS PnL'!G27 -> 59693317
B11: (ii) Interest due on above | E11: ='Note 20-31'!C113 -> 818207.52 | F11: 0
B12: The amount of interest paid by the buyer in terms of section 16 of Micro, Small and Medium Enterprises Devlopment Act,2006, along with the amount of the payment made to the suppliers beyond the appointed day during each accounting year. | E12: 0 | F12: 0
B13: The amount of interest due and payable for the year on delay in making payment (which have been paid but beyond the appointed day during the year) but wihout adding the interest specified under the Micro, Small and Medium Enterprises Development Act,2006,
B14: The amount of interest accrued and remaining unpaid at the end of each accounting year; and | E14: 0 | F14: 0
B15: The amount of further interest remaining due and payable even in the succeeding years,until such date when the interest due above are actually paid to the Small enterprise, for the purpose of disallowances of a deductible expenditure under section 23 of the Micro, Small and Medium Enterprises Devlopment Act,2006, | E15: 0 | F15: 0
A18: Note 33 | B18: Disclosure required under Section 186(4) of the Companies Act, 2013
B20: Amount of Investment:
B21: Name of the Subsidiaries | E21: As at 31st March, 2025 | G21: As at 31st March, 2024
E22: Investment made | F22: Outstanding amount | G22: Investment made | H22: Outstanding amount
B23: ABCD Limited | E23: ='Note (13-20)'!E12 -> 0 | F23: ='Note (13-20)'!F12 -> 1780879.5 | G23: 0 | H23: 1780879.5
B24: ABCDE Private Limited | E24: ='Note (13-20)'!E14 -> 0 | F24: ='Note (13-20)'!F14 -> 2548225 | G24: 0 | H24: 2548225
B26: Amount of loan/advance in the nature of loan:
B27: Name of the Controlled Entity | E27: =E21 -> As at 31st March, 2025 | G27: =G21 -> As at 31st March, 2024
E28: Loan Given | F28: Outstanding amount | G28: Loan Given | H28: Outstanding amount
B29: XYZ Limited | E29: 3915000 | F29: =+'Note (13-20)'!F71 -> 9549877.8 | G29: 18000000 | H29: =+'Note (13-20)'!G71 -> 5852359.5
A31: Note 34 | B31: Solvency
L32: 893598 | M32: 672255
B33: Ratio | D33: Numerator | E33: Denominator | F33: For the year ended March 31, 2025 | G33: For the year ended March 31, 2024 | H33: Variance | I33: Refer | L33: 114196 | M33: 75879
B34: Current Ratio | D34: Current Assets | E34: Current Liabilities | F34: =+Ratio_working!C2/Ratio_working!C3 -> 3.0641629 | G34: =+Ratio_working!D2/Ratio_working!D3 -> 1.083383 | H34: =(F34-G34)/G34 -> 1.8283284 | L34: 93283 | M34: 103313
B35: Debt-Equity Ratio | D35: Total Debt | E35: Shareholder's Equity | F35: =+Ratio_working!C6/Ratio_working!C7 -> 0 | G35: =+Ratio_working!D6/Ratio_working!D7 -> 0.83858763 | H35: =(F35-G35)/G35 -> -1 | I35: i | L35: 39227 | M35: 1011793
B36: Debt Service Converge Ratio | D36: Earning Available for Debt Services | E36: Debt Services | F36: =+Ratio_working!C10/Ratio_working!C11 -> 1.737482 | G36: =+Ratio_working!D10/Ratio_working!D11 -> 0.16366294 | H36: =(F36-G36)/G36 -> 9.6162214 | L36: 320037 | M36: 187000
B37: Return of Equity | D37: Net Profit after Tax | E37: Average Shareholders’ Equity | F37: =+Ratio_working!C15/Ratio_working!C16 -> 0.32394082 | G37: =+Ratio_working!D15/Ratio_working!D16 -> 0.73662935 | H37: =(F37-G37)/G37 -> -0.56023905 | L37: 362946 | M37: 1637000
B38: Inventory Turnover Ratio | D38: Cost of Goods Sold | E38: Average Inventory | F38: =+Ratio_working!C41/Ratio_working!C42 -> 2.8055676 | G38: =+Ratio_working!D41/Ratio_working!D42 -> 5.590831 | H38: =(F38-G38)/G38 -> -0.49818415 | I38: ii | L38: 1146021 | M38: 33637
B39: Trade Receivables Turnover Ratio | D39: Net Credit Sales | E39: Average Accounts Receivable | F39: =+Ratio_working!C19/Ratio_working!C20 -> 4.337018 | G39: =+Ratio_working!D19/Ratio_working!D20 -> 10.058686 | H39: =(F39-G39)/G39 -> -0.56882858 | I39: iii | L39: 2592479 | M39: 1416180
B40: Trade Payables Turnover Ratio | D40: Net Credit Purchases | E40: Average Trade Payables | F40: =+Ratio_working!C23/Ratio_working!C24 -> 11.282118 | G40: =+Ratio_working!D23/Ratio_working!D24 -> 14.704226 | H40: =(F40-G40)/G40 -> -0.23272953 | L40: 826104 | M40: 964134
B41: Working Capital Turnover Ratio | D41: Revenue from operations | E41: Working Capital | F41: =+Ratio_working!C27/Ratio_working!C28 -> 4.8977695 | G41: =+Ratio_working!D27/Ratio_working!D28 -> 31.126 | H41: =(F41-G41)/G41 -> -0.842647 | I41: iv | L41: 193264 | M41: 2895975
B42: Net Profit Ratio | D42: Net Profit after Tax | E42: Net Sales | F42: =+Ratio_working!C32/Ratio_working!C33 -> 0.061384882 | G42: =+Ratio_working!D32/Ratio_working!D33 -> 0.055936286 | H42: =(F42-G42)/G42 -> 0.097407198 | L42: 283286
B43: Return on Capital Employed | D43: Earnings before Interest and Taxes | E43: Capital Employed | F43: =+Ratio_working!C36/Ratio_working!C37 -> 0.13637896 | G43: =+Ratio_working!D36/Ratio_working!D37 -> 0.25452265 | H43: =(F43-G43)/G43 -> -0.46417753 | L43: 1548945
B44: Return on Investment | D44: Income generated from Investments | E44: Time weighted average Investments | F44: NA | G44: NA | H44: NA | L44: 214252
A46: (i) | B46: Repayment of long term loans leads to decrease in ratio.
A47: (ii) | B47: Higher closing inventories leads to decrease in ratio
A48: (iii) | B48: Higher increase in Trade Receivable leads to decrease in ratio
A49: (iv) | B49: Increase in inventories and trade receivables leads to increase in working capital
L50: 1238624
L51: =SUM(L32:L50) -> 9866262 | M51: =SUM(M32:M50) -> 8997166
A53: Note 35 | B53: Contingent liabilities, contingent assets and commitments
B55: Particulars | F55: As at March 31, 2025 | G55: As at March 31, 2024
B56: Contingent liabilities
B57: Claims against the Company, not acknowledged as debts
B58: - Claim by third party | F58: 23001213 | G58: 23001213
B60: Contingent assets
B61: Contingent Assets as on the reporting date | F61: 0 | G61: 0
B63: Commitments
B64: Estimated amount of contracts remaining to be executed on capital account (net of advance) and not provided for | F64: 0 | G64: 0
F65: =SUM(F58:F58) -> 23001213 | G65: =SUM(G58:G58) -> 23001213
A68: Note 36 | B68: Related Party Disclosures
B69: 1. Name of the related parties
B70: (i) …............ (Director)
B71: (ii) …........... (Director)
B72: (iii) Punit Kumar Sarda (Director's Relative)
B73: (iii) ….............. (Director)
B74: (iv) XYZ Private Limited (Common Control)
B75: (v) ABCD Limited (Subsidiary)
B76: (vi) ABCDE Private Limited (Subsidiary)
A78: (ii) | B78: Related parties with whom transactions have taken place during the year alongwith details of such transactions and outstanding balances as at the end of the year:
B79: Name of related party and nature of transactions | D79: Relationship | E79: Nature of Transaction | F79: For the Year ended 31-Mar-2025 | G79: For the Year ended 31-Mar-2024
D81: Director | E81: Director Remuneration
D82: Director | E82: Director Remuneration
D85: Subsidiary | E85: Investment in Equity Shares
D86: Subsidiary | E86: Investment in Equity Shares
D88: Director | E88: Loan Received
D89: Director | E89: Loan Repaid
D90: Director | E90: Loan Outstanding
D92: Director | E92: Loan Received
D93: Director | E93: Loan Repaid
D94: Director | E94: Loan Outstanding
D96: Common Control | E96: Loan and Advance Given
D97: Common Control | E97: Loan Repaid
... D100: Subsidiary | E100: Amount payable/(receivable)
D101: Subsidiary | E101: Purchase of Goods | J101: 40447079 | K101: 20547010 | O101: =+F101-J101-K101 -> -60994089
D102: Subsidiary | E102: Sales of Goods
D103: Subsidiary | E103: Amount Received
D104: Subsidiary | E104: Amount Paid
D105: Subsidiary | E105: Amount payable/(receivable)
A108: Note 37 | B108: Segment Information
B109: The Company primarily operates in - (Object Clause of Company).
A111: Note 38 | B111: Corporate Social Responsibility
B112: The Company is not covered under section 135 of the Companies Act, 2013. Still, the CSR expenditure has been incurred during the financial year ending March 31, 2025. (Previous Year NIL)
G113: =G131 -> For the year ended March 31, 2025 | H113: =H131 -> For the year ended March 31, 2024
B115: Details of CSR expenses
B116: a) Gross amount required to be spent during the year | G116: 1011000 | H116: 0
B117: b) Amount spent during the year | G117: 1050000 | H117: 0
B119: In Cash
B120: i) Construction/acquisition of any asset - | G120: 0 | H120: 0
B121: ii) On purposes other than (i) above | G121: 0 | H121: 0
B123: Yet to be paid in cash
B124: i) Construction/acquisition of any asset - | G124: 0 | H124: 0
B125: ii) On purposes other than (i) above | G125: 0 | H125: 0
A129: Note 39 | B129: The current assets, loans and advances are approximate of the value stated if realized in the ordinary course of business. The provision for all known liabilities are adequate and not in excess of the amount reasonably necessary.
A131: Note 40 | B131: Value of Import on CIF Basis | G131: =+G135 -> For the year ended March 31, 2025 | H131: =+H135 -> For the year ended March 31, 2024
B132: - Raw materials | G132: 1154763.1 | H132: 1276555.5
B133: - Capital goods | G133: 0 | H133: 823658
A135: Note 41 | B135: Earning in Foreign currency | G135: =+F33 -> For the year ended March 31, 2025 | H135: =+G33 -> For the year ended March 31, 2024
B136: Revenue From Operation (Export Sale) | G136: =+'Note 20-31'!C8 -> 8355400 | H136: =+'Note 20-31'!D8 -> 11905200
...

Sheet Stock Reconciliation 
B1: ABC INDIA LIMITED
B2: =Borrowing!A2 -> Notes to financial statements for the year ended at 31st March 2025
B5: Note 46: RECONCILIATION OF QUARTERLY BANK RETURNS | E5: For the year ended 31st March 2025 | I5: For the year ended 31st March 2024
B6: Name of the Bank | D6: Particulars | E6: Quarter | F6: Amount as per books | G6: Amount as per reported in quarterly returns | H6: Amount of Difference | I6: Quarter/ Month | J6: Amount as per books | K6: Amount as per reported in quarterly returns | L6: Amount of Difference
D7: Inventory | H7: =IFERROR(F7-G7,0) -> 0 | L7: =IFERROR(J7-K7,0) -> 0
D8: Debtors | H8: =IFERROR(F8-G8,0) -> 0 | L8: =IFERROR(J8-K8,0) -> 0
D9: Net Total | E9: 45444 | H9: =IFERROR(F9-G9,0) -> 0 | I9: 45078 | L9: =IFERROR(J9-K9,0) -> 0
D10: Inventory | H10: =IFERROR(F10-G10,0) -> 0 | L10: =IFERROR(J10-K10,0) -> 0
D11: Debtors | H11: =IFERROR(F11-G11,0) -> 0 | L11: =IFERROR(J11-K11,0) -> 0
D12: Net Total | E12: 45536 | H12: =IFERROR(F12-G12,0) -> 0 | I12: 45170 | L12: =IFERROR(J12-K12,0) -> 0
D13: Inventory | H13: =IFERROR(F13-G13,0) -> 0 | L13: =IFERROR(J13-K13,0) -> 0
D14: Debtors | H14: =IFERROR(F14-G14,0) -> 0 | L14: =IFERROR(J14-K14,0) -> 0
D15: Net Total | E15: 45627 | H15: =IFERROR(F15-G15,0) -> 0 | I15: 45261 | L15: =IFERROR(J15-K15,0) -> 0
D16: Inventory | H16: =IFERROR(F16-G16,0) -> 0 | L16: =IFERROR(J16-K16,0) -> 0
D17: Debtors | H17: =IFERROR(F17-G17,0) -> 0 | L17: =IFERROR(J17-K17,0) -> 0
D18: Net Total | E18: 45352 | H18: =IFERROR(F18-G18,0) -> 0 | I18: 45352 | L18: =IFERROR(J18-K18,0) -> 0
B22: Note 47: The Company is a Small and Medium Sized Company (SMC) as defined in the General Instructions in respect of Accounting Standards. Accordingly, the Company has complied with the Accounting Standards as applicable to a Small and Medium Sized Company.
B23: \

Sheet Borrowing
A1: ='Note 12 (PPE)'!A1:K1 -> ABC INDIA LIMITED
A2: ='Note 12 (PPE)'!A2 -> Notes to financial statements for the year ended at 31st March 2025
A3: Note No.-45
A4: A. | B4: Term Loan
B5: Sr. No. | C5: Bank Name | D5: Type of loan | E5: As at 31st March 2025 | G5: As at 31st March 2024 | I5: Term of Repayments | L5: Security
E6: Non-Current | F6: Current | G6: Non-Current | H6: Current
B7: Secured- From Banks
B8: 1
B9: =B8+1 -> 2
E10: =SUM(E8:E9) -> 0 | F10: =SUM(F8:F9) -> 0 | G10: =SUM(G8:G9) -> 0 | H10: =SUM(H8:H9) -> 0
B11: Unsecured Loans
B12: 1
B13: =B12+1 -> 2
E14: =SUM(E12:E13) -> 0 | F14: =SUM(F12:F13) -> 0 | G14: =SUM(G12:G13) -> 0 | H14: =SUM(H12:H13) -> 0
B16: Unsecured- From NBFCs
B17: 1
A20: B. | B20: Repayable on demand
B21: Sr. No. | C21: Bank Name | D21: Type of loan | E21: =E5 -> As at 31st March 2025 | G21: As at 31st March 2024 | I21: Term of Repayments | L21: Security
E22: Non-Current | F22: Current | G22: Non-Current | H22: Current
B23: Secured- From Banks
B26: 1
B27: =+B26+1 -> 2
E30: =SUM(E26:E27) -> 0 | F30: =SUM(F26:F27) -> 0 | G30: =SUM(G26:G27) -> 0 | H30: =SUM(H26:H27) -> 0
B31: Unsecured- From NBFC
B32: =B26+1 -> 2
E33: =SUM(E32) -> 0 | F33: =SUM(F32) -> 0 | G33: =SUM(G32) -> 0 | H33: =SUM(H32) -> 0

Sheet EPS
A3: Note 30 | B3: Earning Per Share
C5: For the period ended at March 31, 2025 | D5: ='Note 20-31'!$D$75 -> For the period ended at March 31, 2024
B8: Basic & Diluted Earnings per Share (Rs)
B9: Profit/(Loss) after tax as per Profit & Loss account (Rs) | C9: 65233081 | D9: 58538635
B10: Number of Equity Shares as at beginning of the year | C10: 1662560 | D10: 166256
B11: Number of Equity Shares as at end of the year | C11: 9975360 | D11: 166256
B12: Weighted average number of Equity Shares during the year | C12: 9975360 | D12: 166256
B13: Face value per equity share | C13: 10 | D13: 100
B14: Earnings per Share
B15: Basic | C15: 6.5394212 | D15: 352.09938
B16: Diluted | C16: 6.5394212 | D16: 352.09938
